[
    {
        "hospital_id": "sharp-memorial-hospital",
        "filename": "behavioral-healthSMH4338.xlsx",
        "date": "2019-01-19",
        "uri": "child/adolescent",
        "name": "Child/adolescent",
        "url": "https://www.sharp.com/chargemaster/memorial/upload/SMH4338.xlsx"
    },
    {
        "hospital_id": "sharp-memorial-hospital",
        "filename": "behavioral-healthSMH4349.xlsx",
        "date": "2019-01-19",
        "uri": "dual-recovery-program",
        "name": "Dual recovery program",
        "url": "https://www.sharp.com/chargemaster/memorial/upload/SMH4349.xlsx"
    },
    {
        "hospital_id": "sharp-memorial-hospital",
        "filename": "behavioral-healthSMH4354.xlsx",
        "date": "2019-01-19",
        "uri": "eating-disorders",
        "name": "Eating disorders",
        "url": "https://www.sharp.com/chargemaster/memorial/upload/SMH4354.xlsx"
    },
    {
        "hospital_id": "sharp-memorial-hospital",
        "filename": "behavioral-healthSMH4340.xlsx",
        "date": "2019-01-19",
        "uri": "kearny-mesa",
        "name": "Kearny Mesa",
        "url": "https://www.sharp.com/chargemaster/memorial/upload/SMH4340.xlsx"
    },
    {
        "hospital_id": "sharp-memorial-hospital",
        "filename": "behavioral-healthSMH4341.xlsx",
        "date": "2019-01-19",
        "uri": "mesa-vista-east",
        "name": "Mesa Vista East",
        "url": "https://www.sharp.com/chargemaster/memorial/upload/SMH4341.xlsx"
    },
    {
        "hospital_id": "sharp-memorial-hospital",
        "filename": "behavioral-healthSMH4342.xlsx",
        "date": "2019-01-19",
        "uri": "mesa-vista-east-ii",
        "name": "Mesa Vista East II",
        "url": "https://www.sharp.com/chargemaster/memorial/upload/SMH4342.xlsx"
    },
    {
        "hospital_id": "sharp-memorial-hospital",
        "filename": "behavioral-healthSMH4337.xlsx",
        "date": "2019-01-19",
        "uri": "mesa-vista-east-adolescent",
        "name": "Mesa Vista East adolescent",
        "url": "https://www.sharp.com/chargemaster/memorial/upload/SMH4337.xlsx"
    },
    {
        "hospital_id": "sharp-memorial-hospital",
        "filename": "behavioral-healthSMH4348.xlsx",
        "date": "2019-01-19",
        "uri": "outpatient-program",
        "name": "Outpatient program",
        "url": "https://www.sharp.com/chargemaster/memorial/upload/SMH4348.xlsx"
    },
    {
        "hospital_id": "sharp-memorial-hospital",
        "filename": "behavioral-healthSMH4347.xlsx",
        "date": "2019-01-19",
        "uri": "partial-hospitalization",
        "name": "Partial hospitalization",
        "url": "https://www.sharp.com/chargemaster/memorial/upload/SMH4347.xlsx"
    },
    {
        "hospital_id": "sharp-memorial-hospital",
        "filename": "behavioral-healthSMH4352.xlsx",
        "date": "2019-01-19",
        "uri": "senior-program",
        "name": "Senior program",
        "url": "https://www.sharp.com/chargemaster/memorial/upload/SMH4352.xlsx"
    },
    {
        "hospital_id": "sharp-memorial-hospital",
        "filename": "behavioral-healthSMH4339.xlsx",
        "date": "2019-01-19",
        "uri": "special-services",
        "name": "Special services",
        "url": "https://www.sharp.com/chargemaster/memorial/upload/SMH4339.xlsx"
    },
    {
        "hospital_id": "sharp-memorial-hospital",
        "filename": "behavioral-healthSMH4346.xlsx",
        "date": "2019-01-19",
        "uri": "university-heights",
        "name": "University Heights",
        "url": "https://www.sharp.com/chargemaster/memorial/upload/SMH4346.xlsx"
    },
    {
        "hospital_id": "sharp-memorial-hospital",
        "filename": "acute-care-room-boardSMH3347.xlsx",
        "date": "2019-01-19",
        "uri": "behavioral-health-child/adolescent-unit",
        "name": "Behavioral health child/adolescent unit",
        "url": "https://www.sharp.com/chargemaster/memorial/upload/SMH3347.xlsx"
    },
    {
        "hospital_id": "sharp-memorial-hospital",
        "filename": "acute-care-room-boardSMH3344.xlsx",
        "date": "2019-01-19",
        "uri": "behavioral-health-detox/rehab-unit",
        "name": "Behavioral health detox/rehab unit",
        "url": "https://www.sharp.com/chargemaster/memorial/upload/SMH3344.xlsx"
    },
    {
        "hospital_id": "sharp-memorial-hospital",
        "filename": "acute-care-room-boardSMH3345.xlsx",
        "date": "2019-01-19",
        "uri": "behavioral-health-intensive-care-unit",
        "name": "Behavioral health intensive care unit",
        "url": "https://www.sharp.com/chargemaster/memorial/upload/SMH3345.xlsx"
    },
    {
        "hospital_id": "sharp-memorial-hospital",
        "filename": "acute-care-room-boardSMH3348.xlsx",
        "date": "2019-01-19",
        "uri": "behavioral-health-locked-unit-3342",
        "name": "Behavioral health locked unit 3342",
        "url": "https://www.sharp.com/chargemaster/memorial/upload/SMH3348.xlsx"
    },
    {
        "hospital_id": "sharp-memorial-hospital",
        "filename": "acute-care-room-boardSMH3342.xlsx",
        "date": "2019-01-19",
        "uri": "behavioral-health-locked-unit-3343",
        "name": "Behavioral health locked unit 3343",
        "url": "https://www.sharp.com/chargemaster/memorial/upload/SMH3342.xlsx"
    },
    {
        "hospital_id": "sharp-memorial-hospital",
        "filename": "acute-care-room-boardSMH3176.xlsx",
        "date": "2019-01-19",
        "uri": "gyn/ms-acute",
        "name": "GYN/MS acute",
        "url": "https://www.sharp.com/chargemaster/memorial/upload/SMH3176.xlsx"
    },
    {
        "hospital_id": "sharp-memorial-hospital",
        "filename": "acute-care-room-boardSMH3341.xlsx",
        "date": "2019-01-19",
        "uri": "inpatient-behavioral-health-unit",
        "name": "Inpatient behavioral health unit",
        "url": "https://www.sharp.com/chargemaster/memorial/upload/SMH3341.xlsx"
    },
    {
        "hospital_id": "sharp-memorial-hospital",
        "filename": "acute-care-room-boardSMH3201.xlsx",
        "date": "2019-01-19",
        "uri": "inpatient-rehabilitation-unit",
        "name": "Inpatient rehabilitation unit",
        "url": "https://www.sharp.com/chargemaster/memorial/upload/SMH3201.xlsx"
    },
    {
        "hospital_id": "sharp-memorial-hospital",
        "filename": "acute-care-room-boardSMH3030.xlsx",
        "date": "2019-01-19",
        "uri": "intermediate-care-unit-3030",
        "name": "Intermediate care unit 3030",
        "url": "https://www.sharp.com/chargemaster/memorial/upload/SMH3030.xlsx"
    },
    {
        "hospital_id": "sharp-memorial-hospital",
        "filename": "acute-care-room-boardSMH3031.xlsx",
        "date": "2019-01-19",
        "uri": "intermediate-care-unit-3031",
        "name": "Intermediate care unit 3031",
        "url": "https://www.sharp.com/chargemaster/memorial/upload/SMH3031.xlsx"
    },
    {
        "hospital_id": "sharp-memorial-hospital",
        "filename": "acute-care-room-boardSMH3032.xlsx",
        "date": "2019-01-19",
        "uri": "intermediate-care-unit-3032",
        "name": "Intermediate care unit 3032",
        "url": "https://www.sharp.com/chargemaster/memorial/upload/SMH3032.xlsx"
    },
    {
        "hospital_id": "sharp-memorial-hospital",
        "filename": "acute-care-room-boardSMH3033.xlsx",
        "date": "2019-01-19",
        "uri": "intermediate-care-unit-3033",
        "name": "Intermediate care unit 3033",
        "url": "https://www.sharp.com/chargemaster/memorial/upload/SMH3033.xlsx"
    },
    {
        "hospital_id": "sharp-memorial-hospital",
        "filename": "acute-care-room-boardSMH3082.xlsx",
        "date": "2019-01-19",
        "uri": "intermediate-care-unit-3082",
        "name": "Intermediate care unit 3082",
        "url": "https://www.sharp.com/chargemaster/memorial/upload/SMH3082.xlsx"
    },
    {
        "hospital_id": "sharp-memorial-hospital",
        "filename": "acute-care-room-boardSMH3161.xlsx",
        "date": "2019-01-19",
        "uri": "maternal/infant-services",
        "name": "Maternal/infant services",
        "url": "https://www.sharp.com/chargemaster/memorial/upload/SMH3161.xlsx"
    },
    {
        "hospital_id": "sharp-memorial-hospital",
        "filename": "acute-care-room-boardSMH3420.xlsx",
        "date": "2019-01-19",
        "uri": "sharp-mcdonald-center-chemical-dependency-unit",
        "name": "Sharp McDonald Center chemical dependency unit",
        "url": "https://www.sharp.com/chargemaster/memorial/upload/SMH3420.xlsx"
    },
    {
        "hospital_id": "sharp-memorial-hospital",
        "filename": "acute-care-room-boardSMH3011.xlsx",
        "date": "2019-01-19",
        "uri": "medical-intensive-care-unit-3011",
        "name": "Medical intensive care unit 3011",
        "url": "https://www.sharp.com/chargemaster/memorial/upload/SMH3011.xlsx"
    },
    {
        "hospital_id": "sharp-memorial-hospital",
        "filename": "acute-care-room-boardSMH3015.xlsx",
        "date": "2019-01-19",
        "uri": "medical-intensive-care-unit-3015",
        "name": "Medical intensive care unit 3015",
        "url": "https://www.sharp.com/chargemaster/memorial/upload/SMH3015.xlsx"
    },
    {
        "hospital_id": "sharp-memorial-hospital",
        "filename": "acute-care-room-boardSMH3084.xlsx",
        "date": "2019-01-19",
        "uri": "medical/surgical-3084",
        "name": "Medical/surgical 3084",
        "url": "https://www.sharp.com/chargemaster/memorial/upload/SMH3084.xlsx"
    },
    {
        "hospital_id": "sharp-memorial-hospital",
        "filename": "acute-care-room-boardSMH3085.xlsx",
        "date": "2019-01-19",
        "uri": "medical/surgical-3085",
        "name": "Medical/surgical 3085",
        "url": "https://www.sharp.com/chargemaster/memorial/upload/SMH3085.xlsx"
    },
    {
        "hospital_id": "sharp-memorial-hospital",
        "filename": "acute-care-room-boardSMH3087.xlsx",
        "date": "2019-01-19",
        "uri": "medical/surgical-3087",
        "name": "Medical/surgical 3087",
        "url": "https://www.sharp.com/chargemaster/memorial/upload/SMH3087.xlsx"
    },
    {
        "hospital_id": "sharp-memorial-hospital",
        "filename": "acute-care-room-boardSMH3089.xlsx",
        "date": "2019-01-19",
        "uri": "medical/surgical-3089",
        "name": "Medical/surgical 3089",
        "url": "https://www.sharp.com/chargemaster/memorial/upload/SMH3089.xlsx"
    },
    {
        "hospital_id": "sharp-memorial-hospital",
        "filename": "acute-care-room-boardSMH3181.xlsx",
        "date": "2019-01-19",
        "uri": "medical/surgical-3181",
        "name": "Medical/surgical 3181",
        "url": "https://www.sharp.com/chargemaster/memorial/upload/SMH3181.xlsx"
    },
    {
        "hospital_id": "sharp-memorial-hospital",
        "filename": "acute-care-room-boardSMH3360.xlsx",
        "date": "2019-01-19",
        "uri": "medical/surgical-3360",
        "name": "Medical/surgical 3360",
        "url": "https://www.sharp.com/chargemaster/memorial/upload/SMH3360.xlsx"
    },
    {
        "hospital_id": "sharp-memorial-hospital",
        "filename": "acute-care-room-boardSMH3172.xlsx",
        "date": "2019-01-19",
        "uri": "neonatal-intensive-care-unit",
        "name": "Neonatal intensive care unit",
        "url": "https://www.sharp.com/chargemaster/memorial/upload/SMH3172.xlsx"
    },
    {
        "hospital_id": "sharp-memorial-hospital",
        "filename": "acute-care-room-boardSMH3171.xlsx",
        "date": "2019-01-19",
        "uri": "nursery",
        "name": "Nursery",
        "url": "https://www.sharp.com/chargemaster/memorial/upload/SMH3171.xlsx"
    },
    {
        "hospital_id": "sharp-memorial-hospital",
        "filename": "acute-care-room-boardSMH3163.xlsx",
        "date": "2019-01-19",
        "uri": "obgyn-acute-care-unit",
        "name": "OBGYN acute care unit",
        "url": "https://www.sharp.com/chargemaster/memorial/upload/SMH3163.xlsx"
    },
    {
        "hospital_id": "sharp-memorial-hospital",
        "filename": "acute-care-room-boardSMH3164.xlsx",
        "date": "2019-01-19",
        "uri": "ob-special-care/mis",
        "name": "OB special care/MIS",
        "url": "https://www.sharp.com/chargemaster/memorial/upload/SMH3164.xlsx"
    },
    {
        "hospital_id": "sharp-memorial-hospital",
        "filename": "acute-care-room-boardSMH3162.xlsx",
        "date": "2019-01-19",
        "uri": "obstetrical-special-services",
        "name": "Obstetrical special services",
        "url": "https://www.sharp.com/chargemaster/memorial/upload/SMH3162.xlsx"
    },
    {
        "hospital_id": "sharp-memorial-hospital",
        "filename": "acute-care-room-boardSMH3346.xlsx",
        "date": "2019-01-19",
        "uri": "older-adult-psychiatric-unit",
        "name": "Older adult psychiatric unit",
        "url": "https://www.sharp.com/chargemaster/memorial/upload/SMH3346.xlsx"
    },
    {
        "hospital_id": "sharp-memorial-hospital",
        "filename": "acute-care-room-boardSMH3012.xlsx",
        "date": "2019-01-19",
        "uri": "surgical-intensive-care-unit",
        "name": "Surgical intensive care unit",
        "url": "https://www.sharp.com/chargemaster/memorial/upload/SMH3012.xlsx"
    },
    {
        "hospital_id": "sharp-memorial-hospital",
        "filename": "standard-charges2018-DRG-Files-for-Sharp-update-2019-01-04-com.xlsx",
        "date": "2019-01-19",
        "uri": "standard-charges-for-2019",
        "name": "Standard Charges for 2019",
        "url": "https://www.sharp.com/chargemaster/upload/2018-DRG-Files-for-Sharp-update-2019-01-04-com.xlsx"
    },
    {
        "hospital_id": "sharp-memorial-hospital",
        "filename": "suppliesSMH4052.xlsx",
        "date": "2019-01-19",
        "uri": "central-supply",
        "name": "Central supply",
        "url": "https://www.sharp.com/chargemaster/memorial/upload/SMH4052.xlsx"
    },
    {
        "hospital_id": "sharp-memorial-hospital",
        "filename": "surgerySMH4041.xlsx",
        "date": "2019-01-19",
        "uri": "anesthesiology",
        "name": "Anesthesiology",
        "url": "https://www.sharp.com/chargemaster/memorial/upload/SMH4041.xlsx"
    },
    {
        "hospital_id": "sharp-memorial-hospital",
        "filename": "surgerySMH4231.xlsx",
        "date": "2019-01-19",
        "uri": "endoscopy-services",
        "name": "Endoscopy services",
        "url": "https://www.sharp.com/chargemaster/memorial/upload/SMH4231.xlsx"
    },
    {
        "hospital_id": "sharp-memorial-hospital",
        "filename": "surgerySMH4022.xlsx",
        "date": "2019-01-19",
        "uri": "heart-transplant",
        "name": "Heart transplant",
        "url": "https://www.sharp.com/chargemaster/memorial/upload/SMH4022.xlsx"
    },
    {
        "hospital_id": "sharp-memorial-hospital",
        "filename": "surgerySMH4028.xlsx",
        "date": "2019-01-19",
        "uri": "kidney-transplant",
        "name": "Kidney transplant",
        "url": "https://www.sharp.com/chargemaster/memorial/upload/SMH4028.xlsx"
    },
    {
        "hospital_id": "sharp-memorial-hospital",
        "filename": "surgerySMH4426.xlsx",
        "date": "2019-01-19",
        "uri": "mechanical-assist-program",
        "name": "Mechanical assist program",
        "url": "https://www.sharp.com/chargemaster/memorial/upload/SMH4426.xlsx"
    },
    {
        "hospital_id": "sharp-memorial-hospital",
        "filename": "surgerySMH4035.xlsx",
        "date": "2019-01-19",
        "uri": "outpatient-surgical-center",
        "name": "Outpatient Surgical Center",
        "url": "https://www.sharp.com/chargemaster/memorial/upload/SMH4035.xlsx"
    },
    {
        "hospital_id": "sharp-memorial-hospital",
        "filename": "surgerySMH4021.xlsx",
        "date": "2019-01-19",
        "uri": "surgery/operating-room",
        "name": "Surgery/operating room",
        "url": "https://www.sharp.com/chargemaster/memorial/upload/SMH4021.xlsx"
    },
    {
        "hospital_id": "sharp-memorial-hospital",
        "filename": "surgerySMH4029.xlsx",
        "date": "2019-01-19",
        "uri": "surgery-recovery",
        "name": "Surgery recovery",
        "url": "https://www.sharp.com/chargemaster/memorial/upload/SMH4029.xlsx"
    },
    {
        "hospital_id": "sharp-memorial-hospital",
        "filename": "surgerySMH4052-2.xlsx",
        "date": "2019-01-19",
        "uri": "surgery-supplies",
        "name": "Surgery supplies",
        "url": "https://www.sharp.com/chargemaster/memorial/upload/SMH4052-2.xlsx"
    },
    {
        "hospital_id": "sharp-memorial-hospital",
        "filename": "surgerySMH4175.xlsx",
        "date": "2019-01-19",
        "uri": "vascular-access-service",
        "name": "Vascular access service",
        "url": "https://www.sharp.com/chargemaster/memorial/upload/SMH4175.xlsx"
    },
    {
        "hospital_id": "sharp-memorial-hospital",
        "filename": "other-servicesSMH4801.xlsx",
        "date": "2019-01-19",
        "uri": "audiology",
        "name": "Audiology",
        "url": "https://www.sharp.com/chargemaster/memorial/upload/SMH4801.xlsx"
    },
    {
        "hospital_id": "sharp-memorial-hospital",
        "filename": "other-servicesSMH4417.xlsx",
        "date": "2019-01-19",
        "uri": "diabetes",
        "name": "Diabetes",
        "url": "https://www.sharp.com/chargemaster/memorial/upload/SMH4417.xlsx"
    },
    {
        "hospital_id": "sharp-memorial-hospital",
        "filename": "other-servicesSMH4190.xlsx",
        "date": "2019-01-19",
        "uri": "dialysis",
        "name": "Dialysis",
        "url": "https://www.sharp.com/chargemaster/memorial/upload/SMH4190.xlsx"
    },
    {
        "hospital_id": "sharp-memorial-hospital",
        "filename": "other-servicesSMH4418.xlsx",
        "date": "2019-01-19",
        "uri": "electroconvulsive-therapy",
        "name": "Electroconvulsive therapy",
        "url": "https://www.sharp.com/chargemaster/memorial/upload/SMH4418.xlsx"
    },
    {
        "hospital_id": "sharp-memorial-hospital",
        "filename": "other-servicesSMH4130.xlsx",
        "date": "2019-01-19",
        "uri": "electroencephalography-(eeg)",
        "name": "Electroencephalography (EEG)",
        "url": "https://www.sharp.com/chargemaster/memorial/upload/SMH4130.xlsx"
    },
    {
        "hospital_id": "sharp-memorial-hospital",
        "filename": "other-servicesSMH4091.xlsx",
        "date": "2019-01-19",
        "uri": "endoscopy-services",
        "name": "Endoscopy services",
        "url": "https://www.sharp.com/chargemaster/memorial/upload/SMH4091.xlsx"
    },
    {
        "hospital_id": "sharp-memorial-hospital",
        "filename": "other-servicesSMH4076.xlsx",
        "date": "2019-01-19",
        "uri": "executive-health-services",
        "name": "Executive health services",
        "url": "https://www.sharp.com/chargemaster/memorial/upload/SMH4076.xlsx"
    },
    {
        "hospital_id": "sharp-memorial-hospital",
        "filename": "other-servicesSMH4215.xlsx",
        "date": "2019-01-19",
        "uri": "lymphedema",
        "name": "Lymphedema",
        "url": "https://www.sharp.com/chargemaster/memorial/upload/SMH4215.xlsx"
    },
    {
        "hospital_id": "sharp-memorial-hospital",
        "filename": "other-servicesSMH4332.xlsx",
        "date": "2019-01-19",
        "uri": "nutrition-services",
        "name": "Nutrition services",
        "url": "https://www.sharp.com/chargemaster/memorial/upload/SMH4332.xlsx"
    },
    {
        "hospital_id": "sharp-memorial-hospital",
        "filename": "other-servicesSMH4264.xlsx",
        "date": "2019-01-19",
        "uri": "ophthalmology-clinic",
        "name": "Ophthalmology clinic",
        "url": "https://www.sharp.com/chargemaster/memorial/upload/SMH4264.xlsx"
    },
    {
        "hospital_id": "sharp-memorial-hospital",
        "filename": "other-servicesSMH4176.xlsx",
        "date": "2019-01-19",
        "uri": "op-infusion/oncology-treatment",
        "name": "OP infusion/oncology treatment",
        "url": "https://www.sharp.com/chargemaster/memorial/upload/SMH4176.xlsx"
    },
    {
        "hospital_id": "sharp-memorial-hospital",
        "filename": "other-servicesSMH4185.xlsx",
        "date": "2019-01-19",
        "uri": "pulmonary-rehabilitation",
        "name": "Pulmonary rehabilitation",
        "url": "https://www.sharp.com/chargemaster/memorial/upload/SMH4185.xlsx"
    },
    {
        "hospital_id": "sharp-memorial-hospital",
        "filename": "other-servicesSMH4180.xlsx",
        "date": "2019-01-19",
        "uri": "respiratory-therapy",
        "name": "Respiratory therapy",
        "url": "https://www.sharp.com/chargemaster/memorial/upload/SMH4180.xlsx"
    },
    {
        "hospital_id": "sharp-memorial-hospital",
        "filename": "other-servicesSMH4281.xlsx",
        "date": "2019-01-19",
        "uri": "senior-center",
        "name": "Senior Center",
        "url": "https://www.sharp.com/chargemaster/memorial/upload/SMH4281.xlsx"
    },
    {
        "hospital_id": "sharp-memorial-hospital",
        "filename": "other-servicesSMH4283.xlsx",
        "date": "2019-01-19",
        "uri": "senior-center-ii",
        "name": "Senior Center II",
        "url": "https://www.sharp.com/chargemaster/memorial/upload/SMH4283.xlsx"
    },
    {
        "hospital_id": "sharp-memorial-hospital",
        "filename": "cardiologySMH4116.xlsx",
        "date": "2019-01-19",
        "uri": "cardiac-rehabilitation",
        "name": "Cardiac rehabilitation",
        "url": "https://www.sharp.com/chargemaster/memorial/upload/SMH4116.xlsx"
    },
    {
        "hospital_id": "sharp-memorial-hospital",
        "filename": "cardiologySMH4440.xlsx",
        "date": "2019-01-19",
        "uri": "heart-catheterization-lab",
        "name": "Heart catheterization lab",
        "url": "https://www.sharp.com/chargemaster/memorial/upload/SMH4440.xlsx"
    },
    {
        "hospital_id": "sharp-memorial-hospital",
        "filename": "cardiologySMH4113.xlsx",
        "date": "2019-01-19",
        "uri": "noninvasive-cardiology",
        "name": "Noninvasive cardiology",
        "url": "https://www.sharp.com/chargemaster/memorial/upload/SMH4113.xlsx"
    },
    {
        "hospital_id": "sharp-memorial-hospital",
        "filename": "cardiologySMH4112.xlsx",
        "date": "2019-01-19",
        "uri": "vascular-lab",
        "name": "Vascular lab",
        "url": "https://www.sharp.com/chargemaster/memorial/upload/SMH4112.xlsx"
    },
    {
        "hospital_id": "sharp-memorial-hospital",
        "filename": "emergencySMH4231-2.xlsx",
        "date": "2019-01-19",
        "uri": "emergency",
        "name": "Emergency",
        "url": "https://www.sharp.com/chargemaster/memorial/upload/SMH4231-2.xlsx"
    },
    {
        "hospital_id": "sharp-memorial-hospital",
        "filename": "laboratorySMH4102.xlsx",
        "date": "2019-01-19",
        "uri": "blood-bank-products",
        "name": "Blood bank products",
        "url": "https://www.sharp.com/chargemaster/memorial/upload/SMH4102.xlsx"
    },
    {
        "hospital_id": "sharp-memorial-hospital",
        "filename": "laboratorySMH4065.xlsx",
        "date": "2019-01-19",
        "uri": "clinical-laboratory",
        "name": "Clinical laboratory",
        "url": "https://www.sharp.com/chargemaster/memorial/upload/SMH4065.xlsx"
    },
    {
        "hospital_id": "sharp-memorial-hospital",
        "filename": "laboratorySMH4068.xlsx",
        "date": "2019-01-19",
        "uri": "hla-laboratory",
        "name": "HLA laboratory",
        "url": "https://www.sharp.com/chargemaster/memorial/upload/SMH4068.xlsx"
    },
    {
        "hospital_id": "sharp-memorial-hospital",
        "filename": "laboratorySMH4063.xlsx",
        "date": "2019-01-19",
        "uri": "lab-copley-clinical",
        "name": "Lab Copley clinical",
        "url": "https://www.sharp.com/chargemaster/memorial/upload/SMH4063.xlsx"
    },
    {
        "hospital_id": "sharp-memorial-hospital",
        "filename": "laboratorySMH4062.xlsx",
        "date": "2019-01-19",
        "uri": "lab-copley-microbiology",
        "name": "Lab Copley microbiology",
        "url": "https://www.sharp.com/chargemaster/memorial/upload/SMH4062.xlsx"
    },
    {
        "hospital_id": "sharp-memorial-hospital",
        "filename": "laboratorySMH4066.xlsx",
        "date": "2019-01-19",
        "uri": "lab-send-out-tests",
        "name": "Lab send out tests",
        "url": "https://www.sharp.com/chargemaster/memorial/upload/SMH4066.xlsx"
    },
    {
        "hospital_id": "sharp-memorial-hospital",
        "filename": "laboratorySMH4070.xlsx",
        "date": "2019-01-19",
        "uri": "pathology",
        "name": "Pathology",
        "url": "https://www.sharp.com/chargemaster/memorial/upload/SMH4070.xlsx"
    },
    {
        "hospital_id": "sharp-memorial-hospital",
        "filename": "pharmacySMH4171.xlsx",
        "date": "2019-01-19",
        "uri": "pharmacy",
        "name": "Pharmacy",
        "url": "https://www.sharp.com/chargemaster/memorial/upload/SMH4171.xlsx"
    },
    {
        "hospital_id": "sharp-memorial-hospital",
        "filename": "radiologySMH4421.xlsx",
        "date": "2019-01-19",
        "uri": "computerized-tomography-(ct)-scanning",
        "name": "Computerized tomography (CT) scanning",
        "url": "https://www.sharp.com/chargemaster/memorial/upload/SMH4421.xlsx"
    },
    {
        "hospital_id": "sharp-memorial-hospital",
        "filename": "radiologySMH4142.xlsx",
        "date": "2019-01-19",
        "uri": "general-radiology",
        "name": "General radiology",
        "url": "https://www.sharp.com/chargemaster/memorial/upload/SMH4142.xlsx"
    },
    {
        "hospital_id": "sharp-memorial-hospital",
        "filename": "radiologySMH4165.xlsx",
        "date": "2019-01-19",
        "uri": "imaging-offices",
        "name": "Imaging offices",
        "url": "https://www.sharp.com/chargemaster/memorial/upload/SMH4165.xlsx"
    },
    {
        "hospital_id": "sharp-memorial-hospital",
        "filename": "radiologySMH4425.xlsx",
        "date": "2019-01-19",
        "uri": "magnetic-resonance-imaging-(mri)",
        "name": "Magnetic resonance imaging (MRI)",
        "url": "https://www.sharp.com/chargemaster/memorial/upload/SMH4425.xlsx"
    },
    {
        "hospital_id": "sharp-memorial-hospital",
        "filename": "radiologySMH4160.xlsx",
        "date": "2019-01-19",
        "uri": "nuclear-medicine",
        "name": "Nuclear medicine",
        "url": "https://www.sharp.com/chargemaster/memorial/upload/SMH4160.xlsx"
    },
    {
        "hospital_id": "sharp-memorial-hospital",
        "filename": "radiologySMH4162.xlsx",
        "date": "2019-01-19",
        "uri": "positron-emission-tomography-(pet)",
        "name": "Positron emission tomography (PET)",
        "url": "https://www.sharp.com/chargemaster/memorial/upload/SMH4162.xlsx"
    },
    {
        "hospital_id": "sharp-memorial-hospital",
        "filename": "radiologySMH4152.xlsx",
        "date": "2019-01-19",
        "uri": "radiation-oncology-treatment",
        "name": "Radiation oncology treatment",
        "url": "https://www.sharp.com/chargemaster/memorial/upload/SMH4152.xlsx"
    },
    {
        "hospital_id": "sharp-memorial-hospital",
        "filename": "radiologySMH4144.xlsx",
        "date": "2019-01-19",
        "uri": "radiology-special-procedure",
        "name": "Radiology special procedure",
        "url": "https://www.sharp.com/chargemaster/memorial/upload/SMH4144.xlsx"
    },
    {
        "hospital_id": "sharp-memorial-hospital",
        "filename": "radiologySMH4143.xlsx",
        "date": "2019-01-19",
        "uri": "ultrasound",
        "name": "Ultrasound",
        "url": "https://www.sharp.com/chargemaster/memorial/upload/SMH4143.xlsx"
    },
    {
        "hospital_id": "sharp-memorial-hospital",
        "filename": "rehabilitationSMH4211.xlsx",
        "date": "2019-01-19",
        "uri": "occupational-therapy-treatment",
        "name": "Occupational therapy treatment",
        "url": "https://www.sharp.com/chargemaster/memorial/upload/SMH4211.xlsx"
    },
    {
        "hospital_id": "sharp-memorial-hospital",
        "filename": "rehabilitationSMH4411.xlsx",
        "date": "2019-01-19",
        "uri": "outpatient-psychiatric-services",
        "name": "Outpatient psychiatric services",
        "url": "https://www.sharp.com/chargemaster/memorial/upload/SMH4411.xlsx"
    },
    {
        "hospital_id": "sharp-memorial-hospital",
        "filename": "rehabilitationSMH4200.xlsx",
        "date": "2019-01-19",
        "uri": "physical-therapy-clinic",
        "name": "Physical therapy clinic",
        "url": "https://www.sharp.com/chargemaster/memorial/upload/SMH4200.xlsx"
    },
    {
        "hospital_id": "sharp-memorial-hospital",
        "filename": "rehabilitationSMH4201.xlsx",
        "date": "2019-01-19",
        "uri": "physical-therapy-general-treatment",
        "name": "Physical therapy general treatment",
        "url": "https://www.sharp.com/chargemaster/memorial/upload/SMH4201.xlsx"
    },
    {
        "hospital_id": "sharp-memorial-hospital",
        "filename": "rehabilitationSMH4280.xlsx",
        "date": "2019-01-19",
        "uri": "rehab-clinic",
        "name": "Rehab clinic",
        "url": "https://www.sharp.com/chargemaster/memorial/upload/SMH4280.xlsx"
    },
    {
        "hospital_id": "sharp-memorial-hospital",
        "filename": "rehabilitationSMH4413.xlsx",
        "date": "2019-01-19",
        "uri": "rehabilitation-pain-program",
        "name": "Rehabilitation pain program",
        "url": "https://www.sharp.com/chargemaster/memorial/upload/SMH4413.xlsx"
    },
    {
        "hospital_id": "sharp-memorial-hospital",
        "filename": "rehabilitationSMH4414.xlsx",
        "date": "2019-01-19",
        "uri": "rehabilitation-day-treatment",
        "name": "Rehabilitation day treatment",
        "url": "https://www.sharp.com/chargemaster/memorial/upload/SMH4414.xlsx"
    },
    {
        "hospital_id": "sharp-memorial-hospital",
        "filename": "rehabilitationSMH4221.xlsx",
        "date": "2019-01-19",
        "uri": "speech-therapy",
        "name": "Speech therapy",
        "url": "https://www.sharp.com/chargemaster/memorial/upload/SMH4221.xlsx"
    },
    {
        "hospital_id": "sharp-memorial-hospital",
        "filename": "womens-servicesSMH4018.xlsx",
        "date": "2019-01-19",
        "uri": "antenatal-testing",
        "name": "Antenatal testing",
        "url": "https://www.sharp.com/chargemaster/memorial/upload/SMH4018.xlsx"
    },
    {
        "hospital_id": "sharp-memorial-hospital",
        "filename": "womens-servicesSMH4010.xlsx",
        "date": "2019-01-19",
        "uri": "infant-clinic",
        "name": "Infant clinic",
        "url": "https://www.sharp.com/chargemaster/memorial/upload/SMH4010.xlsx"
    },
    {
        "hospital_id": "sharp-memorial-hospital",
        "filename": "womens-servicesSMH4011.xlsx",
        "date": "2019-01-19",
        "uri": "labor-and-delivery",
        "name": "Labor and delivery",
        "url": "https://www.sharp.com/chargemaster/memorial/upload/SMH4011.xlsx"
    },
    {
        "hospital_id": "sharp-memorial-hospital",
        "filename": "womens-servicesSMH4019.xlsx",
        "date": "2019-01-19",
        "uri": "lactation",
        "name": "Lactation",
        "url": "https://www.sharp.com/chargemaster/memorial/upload/SMH4019.xlsx"
    },
    {
        "hospital_id": "sharp-memorial-hospital",
        "filename": "womens-servicesSMH4012.xlsx",
        "date": "2019-01-19",
        "uri": "surgical-gynecology",
        "name": "Surgical gynecology",
        "url": "https://www.sharp.com/chargemaster/memorial/upload/SMH4012.xlsx"
    },
    {
        "hospital_id": "sharp-memorial-hospital",
        "filename": "womens-servicesSMH4016.xlsx",
        "date": "2019-01-19",
        "uri": "women's-center-recovery",
        "name": "Women's center recovery",
        "url": "https://www.sharp.com/chargemaster/memorial/upload/SMH4016.xlsx"
    },
    {
        "hospital_id": "sharp-memorial-hospital",
        "filename": "womens-servicesSMH4014.xlsx",
        "date": "2019-01-19",
        "uri": "women's-triage",
        "name": "Women's triage",
        "url": "https://www.sharp.com/chargemaster/memorial/upload/SMH4014.xlsx"
    },
    {
        "hospital_id": "sharp-memorial-hospital",
        "filename": "behavioral-healthSMH4338.xlsx",
        "date": "2019-01-19",
        "uri": "child/adolescent",
        "name": "Child/adolescent",
        "url": "https://www.sharp.com/chargemaster/memorial/upload/SMH4338.xlsx"
    },
    {
        "hospital_id": "sharp-memorial-hospital",
        "filename": "behavioral-healthSMH4349.xlsx",
        "date": "2019-01-19",
        "uri": "dual-recovery-program",
        "name": "Dual recovery program",
        "url": "https://www.sharp.com/chargemaster/memorial/upload/SMH4349.xlsx"
    },
    {
        "hospital_id": "sharp-memorial-hospital",
        "filename": "behavioral-healthSMH4354.xlsx",
        "date": "2019-01-19",
        "uri": "eating-disorders",
        "name": "Eating disorders",
        "url": "https://www.sharp.com/chargemaster/memorial/upload/SMH4354.xlsx"
    },
    {
        "hospital_id": "sharp-memorial-hospital",
        "filename": "behavioral-healthSMH4340.xlsx",
        "date": "2019-01-19",
        "uri": "kearny-mesa",
        "name": "Kearny Mesa",
        "url": "https://www.sharp.com/chargemaster/memorial/upload/SMH4340.xlsx"
    },
    {
        "hospital_id": "sharp-memorial-hospital",
        "filename": "behavioral-healthSMH4341.xlsx",
        "date": "2019-01-19",
        "uri": "mesa-vista-east",
        "name": "Mesa Vista East",
        "url": "https://www.sharp.com/chargemaster/memorial/upload/SMH4341.xlsx"
    },
    {
        "hospital_id": "sharp-memorial-hospital",
        "filename": "behavioral-healthSMH4342.xlsx",
        "date": "2019-01-19",
        "uri": "mesa-vista-east-ii",
        "name": "Mesa Vista East II",
        "url": "https://www.sharp.com/chargemaster/memorial/upload/SMH4342.xlsx"
    },
    {
        "hospital_id": "sharp-memorial-hospital",
        "filename": "behavioral-healthSMH4337.xlsx",
        "date": "2019-01-19",
        "uri": "mesa-vista-east-adolescent",
        "name": "Mesa Vista East adolescent",
        "url": "https://www.sharp.com/chargemaster/memorial/upload/SMH4337.xlsx"
    },
    {
        "hospital_id": "sharp-memorial-hospital",
        "filename": "behavioral-healthSMH4348.xlsx",
        "date": "2019-01-19",
        "uri": "outpatient-program",
        "name": "Outpatient program",
        "url": "https://www.sharp.com/chargemaster/memorial/upload/SMH4348.xlsx"
    },
    {
        "hospital_id": "sharp-memorial-hospital",
        "filename": "behavioral-healthSMH4347.xlsx",
        "date": "2019-01-19",
        "uri": "partial-hospitalization",
        "name": "Partial hospitalization",
        "url": "https://www.sharp.com/chargemaster/memorial/upload/SMH4347.xlsx"
    },
    {
        "hospital_id": "sharp-memorial-hospital",
        "filename": "behavioral-healthSMH4352.xlsx",
        "date": "2019-01-19",
        "uri": "senior-program",
        "name": "Senior program",
        "url": "https://www.sharp.com/chargemaster/memorial/upload/SMH4352.xlsx"
    },
    {
        "hospital_id": "sharp-memorial-hospital",
        "filename": "behavioral-healthSMH4339.xlsx",
        "date": "2019-01-19",
        "uri": "special-services",
        "name": "Special services",
        "url": "https://www.sharp.com/chargemaster/memorial/upload/SMH4339.xlsx"
    },
    {
        "hospital_id": "sharp-memorial-hospital",
        "filename": "behavioral-healthSMH4346.xlsx",
        "date": "2019-01-19",
        "uri": "university-heights",
        "name": "University Heights",
        "url": "https://www.sharp.com/chargemaster/memorial/upload/SMH4346.xlsx"
    },
    {
        "hospital_id": "sharp-memorial-hospital",
        "filename": "acute-care-room-boardSMH3347.xlsx",
        "date": "2019-01-19",
        "uri": "behavioral-health-child/adolescent-unit",
        "name": "Behavioral health child/adolescent unit",
        "url": "https://www.sharp.com/chargemaster/memorial/upload/SMH3347.xlsx"
    },
    {
        "hospital_id": "sharp-memorial-hospital",
        "filename": "acute-care-room-boardSMH3344.xlsx",
        "date": "2019-01-19",
        "uri": "behavioral-health-detox/rehab-unit",
        "name": "Behavioral health detox/rehab unit",
        "url": "https://www.sharp.com/chargemaster/memorial/upload/SMH3344.xlsx"
    },
    {
        "hospital_id": "sharp-memorial-hospital",
        "filename": "acute-care-room-boardSMH3345.xlsx",
        "date": "2019-01-19",
        "uri": "behavioral-health-intensive-care-unit",
        "name": "Behavioral health intensive care unit",
        "url": "https://www.sharp.com/chargemaster/memorial/upload/SMH3345.xlsx"
    },
    {
        "hospital_id": "sharp-memorial-hospital",
        "filename": "acute-care-room-boardSMH3348.xlsx",
        "date": "2019-01-19",
        "uri": "behavioral-health-locked-unit-3342",
        "name": "Behavioral health locked unit 3342",
        "url": "https://www.sharp.com/chargemaster/memorial/upload/SMH3348.xlsx"
    },
    {
        "hospital_id": "sharp-memorial-hospital",
        "filename": "acute-care-room-boardSMH3342.xlsx",
        "date": "2019-01-19",
        "uri": "behavioral-health-locked-unit-3343",
        "name": "Behavioral health locked unit 3343",
        "url": "https://www.sharp.com/chargemaster/memorial/upload/SMH3342.xlsx"
    },
    {
        "hospital_id": "sharp-memorial-hospital",
        "filename": "acute-care-room-boardSMH3176.xlsx",
        "date": "2019-01-19",
        "uri": "gyn/ms-acute",
        "name": "GYN/MS acute",
        "url": "https://www.sharp.com/chargemaster/memorial/upload/SMH3176.xlsx"
    },
    {
        "hospital_id": "sharp-memorial-hospital",
        "filename": "acute-care-room-boardSMH3341.xlsx",
        "date": "2019-01-19",
        "uri": "inpatient-behavioral-health-unit",
        "name": "Inpatient behavioral health unit",
        "url": "https://www.sharp.com/chargemaster/memorial/upload/SMH3341.xlsx"
    },
    {
        "hospital_id": "sharp-memorial-hospital",
        "filename": "acute-care-room-boardSMH3201.xlsx",
        "date": "2019-01-19",
        "uri": "inpatient-rehabilitation-unit",
        "name": "Inpatient rehabilitation unit",
        "url": "https://www.sharp.com/chargemaster/memorial/upload/SMH3201.xlsx"
    },
    {
        "hospital_id": "sharp-memorial-hospital",
        "filename": "acute-care-room-boardSMH3030.xlsx",
        "date": "2019-01-19",
        "uri": "intermediate-care-unit-3030",
        "name": "Intermediate care unit 3030",
        "url": "https://www.sharp.com/chargemaster/memorial/upload/SMH3030.xlsx"
    },
    {
        "hospital_id": "sharp-memorial-hospital",
        "filename": "acute-care-room-boardSMH3031.xlsx",
        "date": "2019-01-19",
        "uri": "intermediate-care-unit-3031",
        "name": "Intermediate care unit 3031",
        "url": "https://www.sharp.com/chargemaster/memorial/upload/SMH3031.xlsx"
    },
    {
        "hospital_id": "sharp-memorial-hospital",
        "filename": "acute-care-room-boardSMH3032.xlsx",
        "date": "2019-01-19",
        "uri": "intermediate-care-unit-3032",
        "name": "Intermediate care unit 3032",
        "url": "https://www.sharp.com/chargemaster/memorial/upload/SMH3032.xlsx"
    },
    {
        "hospital_id": "sharp-memorial-hospital",
        "filename": "acute-care-room-boardSMH3033.xlsx",
        "date": "2019-01-19",
        "uri": "intermediate-care-unit-3033",
        "name": "Intermediate care unit 3033",
        "url": "https://www.sharp.com/chargemaster/memorial/upload/SMH3033.xlsx"
    },
    {
        "hospital_id": "sharp-memorial-hospital",
        "filename": "acute-care-room-boardSMH3082.xlsx",
        "date": "2019-01-19",
        "uri": "intermediate-care-unit-3082",
        "name": "Intermediate care unit 3082",
        "url": "https://www.sharp.com/chargemaster/memorial/upload/SMH3082.xlsx"
    },
    {
        "hospital_id": "sharp-memorial-hospital",
        "filename": "acute-care-room-boardSMH3161.xlsx",
        "date": "2019-01-19",
        "uri": "maternal/infant-services",
        "name": "Maternal/infant services",
        "url": "https://www.sharp.com/chargemaster/memorial/upload/SMH3161.xlsx"
    },
    {
        "hospital_id": "sharp-memorial-hospital",
        "filename": "acute-care-room-boardSMH3420.xlsx",
        "date": "2019-01-19",
        "uri": "sharp-mcdonald-center-chemical-dependency-unit",
        "name": "Sharp McDonald Center chemical dependency unit",
        "url": "https://www.sharp.com/chargemaster/memorial/upload/SMH3420.xlsx"
    },
    {
        "hospital_id": "sharp-memorial-hospital",
        "filename": "acute-care-room-boardSMH3011.xlsx",
        "date": "2019-01-19",
        "uri": "medical-intensive-care-unit-3011",
        "name": "Medical intensive care unit 3011",
        "url": "https://www.sharp.com/chargemaster/memorial/upload/SMH3011.xlsx"
    },
    {
        "hospital_id": "sharp-memorial-hospital",
        "filename": "acute-care-room-boardSMH3015.xlsx",
        "date": "2019-01-19",
        "uri": "medical-intensive-care-unit-3015",
        "name": "Medical intensive care unit 3015",
        "url": "https://www.sharp.com/chargemaster/memorial/upload/SMH3015.xlsx"
    },
    {
        "hospital_id": "sharp-memorial-hospital",
        "filename": "acute-care-room-boardSMH3084.xlsx",
        "date": "2019-01-19",
        "uri": "medical/surgical-3084",
        "name": "Medical/surgical 3084",
        "url": "https://www.sharp.com/chargemaster/memorial/upload/SMH3084.xlsx"
    },
    {
        "hospital_id": "sharp-memorial-hospital",
        "filename": "acute-care-room-boardSMH3085.xlsx",
        "date": "2019-01-19",
        "uri": "medical/surgical-3085",
        "name": "Medical/surgical 3085",
        "url": "https://www.sharp.com/chargemaster/memorial/upload/SMH3085.xlsx"
    },
    {
        "hospital_id": "sharp-memorial-hospital",
        "filename": "acute-care-room-boardSMH3087.xlsx",
        "date": "2019-01-19",
        "uri": "medical/surgical-3087",
        "name": "Medical/surgical 3087",
        "url": "https://www.sharp.com/chargemaster/memorial/upload/SMH3087.xlsx"
    },
    {
        "hospital_id": "sharp-memorial-hospital",
        "filename": "acute-care-room-boardSMH3089.xlsx",
        "date": "2019-01-19",
        "uri": "medical/surgical-3089",
        "name": "Medical/surgical 3089",
        "url": "https://www.sharp.com/chargemaster/memorial/upload/SMH3089.xlsx"
    },
    {
        "hospital_id": "sharp-memorial-hospital",
        "filename": "acute-care-room-boardSMH3181.xlsx",
        "date": "2019-01-19",
        "uri": "medical/surgical-3181",
        "name": "Medical/surgical 3181",
        "url": "https://www.sharp.com/chargemaster/memorial/upload/SMH3181.xlsx"
    },
    {
        "hospital_id": "sharp-memorial-hospital",
        "filename": "acute-care-room-boardSMH3360.xlsx",
        "date": "2019-01-19",
        "uri": "medical/surgical-3360",
        "name": "Medical/surgical 3360",
        "url": "https://www.sharp.com/chargemaster/memorial/upload/SMH3360.xlsx"
    },
    {
        "hospital_id": "sharp-memorial-hospital",
        "filename": "acute-care-room-boardSMH3172.xlsx",
        "date": "2019-01-19",
        "uri": "neonatal-intensive-care-unit",
        "name": "Neonatal intensive care unit",
        "url": "https://www.sharp.com/chargemaster/memorial/upload/SMH3172.xlsx"
    },
    {
        "hospital_id": "sharp-memorial-hospital",
        "filename": "acute-care-room-boardSMH3171.xlsx",
        "date": "2019-01-19",
        "uri": "nursery",
        "name": "Nursery",
        "url": "https://www.sharp.com/chargemaster/memorial/upload/SMH3171.xlsx"
    },
    {
        "hospital_id": "sharp-memorial-hospital",
        "filename": "acute-care-room-boardSMH3163.xlsx",
        "date": "2019-01-19",
        "uri": "obgyn-acute-care-unit",
        "name": "OBGYN acute care unit",
        "url": "https://www.sharp.com/chargemaster/memorial/upload/SMH3163.xlsx"
    },
    {
        "hospital_id": "sharp-memorial-hospital",
        "filename": "acute-care-room-boardSMH3164.xlsx",
        "date": "2019-01-19",
        "uri": "ob-special-care/mis",
        "name": "OB special care/MIS",
        "url": "https://www.sharp.com/chargemaster/memorial/upload/SMH3164.xlsx"
    },
    {
        "hospital_id": "sharp-memorial-hospital",
        "filename": "acute-care-room-boardSMH3162.xlsx",
        "date": "2019-01-19",
        "uri": "obstetrical-special-services",
        "name": "Obstetrical special services",
        "url": "https://www.sharp.com/chargemaster/memorial/upload/SMH3162.xlsx"
    },
    {
        "hospital_id": "sharp-memorial-hospital",
        "filename": "acute-care-room-boardSMH3346.xlsx",
        "date": "2019-01-19",
        "uri": "older-adult-psychiatric-unit",
        "name": "Older adult psychiatric unit",
        "url": "https://www.sharp.com/chargemaster/memorial/upload/SMH3346.xlsx"
    },
    {
        "hospital_id": "sharp-memorial-hospital",
        "filename": "acute-care-room-boardSMH3012.xlsx",
        "date": "2019-01-19",
        "uri": "surgical-intensive-care-unit",
        "name": "Surgical intensive care unit",
        "url": "https://www.sharp.com/chargemaster/memorial/upload/SMH3012.xlsx"
    },
    {
        "hospital_id": "sharp-memorial-hospital",
        "filename": "standard-charges2018-DRG-Files-for-Sharp-update-2019-01-04-com.xlsx",
        "date": "2019-01-19",
        "uri": "standard-charges-for-2019",
        "name": "Standard Charges for 2019",
        "url": "https://www.sharp.com/chargemaster/upload/2018-DRG-Files-for-Sharp-update-2019-01-04-com.xlsx"
    },
    {
        "hospital_id": "sharp-memorial-hospital",
        "filename": "suppliesSMH4052.xlsx",
        "date": "2019-01-19",
        "uri": "central-supply",
        "name": "Central supply",
        "url": "https://www.sharp.com/chargemaster/memorial/upload/SMH4052.xlsx"
    },
    {
        "hospital_id": "sharp-memorial-hospital",
        "filename": "surgerySMH4041.xlsx",
        "date": "2019-01-19",
        "uri": "anesthesiology",
        "name": "Anesthesiology",
        "url": "https://www.sharp.com/chargemaster/memorial/upload/SMH4041.xlsx"
    },
    {
        "hospital_id": "sharp-memorial-hospital",
        "filename": "surgerySMH4231.xlsx",
        "date": "2019-01-19",
        "uri": "endoscopy-services",
        "name": "Endoscopy services",
        "url": "https://www.sharp.com/chargemaster/memorial/upload/SMH4231.xlsx"
    },
    {
        "hospital_id": "sharp-memorial-hospital",
        "filename": "surgerySMH4022.xlsx",
        "date": "2019-01-19",
        "uri": "heart-transplant",
        "name": "Heart transplant",
        "url": "https://www.sharp.com/chargemaster/memorial/upload/SMH4022.xlsx"
    },
    {
        "hospital_id": "sharp-memorial-hospital",
        "filename": "surgerySMH4028.xlsx",
        "date": "2019-01-19",
        "uri": "kidney-transplant",
        "name": "Kidney transplant",
        "url": "https://www.sharp.com/chargemaster/memorial/upload/SMH4028.xlsx"
    },
    {
        "hospital_id": "sharp-memorial-hospital",
        "filename": "surgerySMH4426.xlsx",
        "date": "2019-01-19",
        "uri": "mechanical-assist-program",
        "name": "Mechanical assist program",
        "url": "https://www.sharp.com/chargemaster/memorial/upload/SMH4426.xlsx"
    },
    {
        "hospital_id": "sharp-memorial-hospital",
        "filename": "surgerySMH4035.xlsx",
        "date": "2019-01-19",
        "uri": "outpatient-surgical-center",
        "name": "Outpatient Surgical Center",
        "url": "https://www.sharp.com/chargemaster/memorial/upload/SMH4035.xlsx"
    },
    {
        "hospital_id": "sharp-memorial-hospital",
        "filename": "surgerySMH4021.xlsx",
        "date": "2019-01-19",
        "uri": "surgery/operating-room",
        "name": "Surgery/operating room",
        "url": "https://www.sharp.com/chargemaster/memorial/upload/SMH4021.xlsx"
    },
    {
        "hospital_id": "sharp-memorial-hospital",
        "filename": "surgerySMH4029.xlsx",
        "date": "2019-01-19",
        "uri": "surgery-recovery",
        "name": "Surgery recovery",
        "url": "https://www.sharp.com/chargemaster/memorial/upload/SMH4029.xlsx"
    },
    {
        "hospital_id": "sharp-memorial-hospital",
        "filename": "surgerySMH4052-2.xlsx",
        "date": "2019-01-19",
        "uri": "surgery-supplies",
        "name": "Surgery supplies",
        "url": "https://www.sharp.com/chargemaster/memorial/upload/SMH4052-2.xlsx"
    },
    {
        "hospital_id": "sharp-memorial-hospital",
        "filename": "surgerySMH4175.xlsx",
        "date": "2019-01-19",
        "uri": "vascular-access-service",
        "name": "Vascular access service",
        "url": "https://www.sharp.com/chargemaster/memorial/upload/SMH4175.xlsx"
    },
    {
        "hospital_id": "sharp-memorial-hospital",
        "filename": "other-servicesSMH4801.xlsx",
        "date": "2019-01-19",
        "uri": "audiology",
        "name": "Audiology",
        "url": "https://www.sharp.com/chargemaster/memorial/upload/SMH4801.xlsx"
    },
    {
        "hospital_id": "sharp-memorial-hospital",
        "filename": "other-servicesSMH4417.xlsx",
        "date": "2019-01-19",
        "uri": "diabetes",
        "name": "Diabetes",
        "url": "https://www.sharp.com/chargemaster/memorial/upload/SMH4417.xlsx"
    },
    {
        "hospital_id": "sharp-memorial-hospital",
        "filename": "other-servicesSMH4190.xlsx",
        "date": "2019-01-19",
        "uri": "dialysis",
        "name": "Dialysis",
        "url": "https://www.sharp.com/chargemaster/memorial/upload/SMH4190.xlsx"
    },
    {
        "hospital_id": "sharp-memorial-hospital",
        "filename": "other-servicesSMH4418.xlsx",
        "date": "2019-01-19",
        "uri": "electroconvulsive-therapy",
        "name": "Electroconvulsive therapy",
        "url": "https://www.sharp.com/chargemaster/memorial/upload/SMH4418.xlsx"
    },
    {
        "hospital_id": "sharp-memorial-hospital",
        "filename": "other-servicesSMH4130.xlsx",
        "date": "2019-01-19",
        "uri": "electroencephalography-(eeg)",
        "name": "Electroencephalography (EEG)",
        "url": "https://www.sharp.com/chargemaster/memorial/upload/SMH4130.xlsx"
    },
    {
        "hospital_id": "sharp-memorial-hospital",
        "filename": "other-servicesSMH4091.xlsx",
        "date": "2019-01-19",
        "uri": "endoscopy-services",
        "name": "Endoscopy services",
        "url": "https://www.sharp.com/chargemaster/memorial/upload/SMH4091.xlsx"
    },
    {
        "hospital_id": "sharp-memorial-hospital",
        "filename": "other-servicesSMH4076.xlsx",
        "date": "2019-01-19",
        "uri": "executive-health-services",
        "name": "Executive health services",
        "url": "https://www.sharp.com/chargemaster/memorial/upload/SMH4076.xlsx"
    },
    {
        "hospital_id": "sharp-memorial-hospital",
        "filename": "other-servicesSMH4215.xlsx",
        "date": "2019-01-19",
        "uri": "lymphedema",
        "name": "Lymphedema",
        "url": "https://www.sharp.com/chargemaster/memorial/upload/SMH4215.xlsx"
    },
    {
        "hospital_id": "sharp-memorial-hospital",
        "filename": "other-servicesSMH4332.xlsx",
        "date": "2019-01-19",
        "uri": "nutrition-services",
        "name": "Nutrition services",
        "url": "https://www.sharp.com/chargemaster/memorial/upload/SMH4332.xlsx"
    },
    {
        "hospital_id": "sharp-memorial-hospital",
        "filename": "other-servicesSMH4264.xlsx",
        "date": "2019-01-19",
        "uri": "ophthalmology-clinic",
        "name": "Ophthalmology clinic",
        "url": "https://www.sharp.com/chargemaster/memorial/upload/SMH4264.xlsx"
    },
    {
        "hospital_id": "sharp-memorial-hospital",
        "filename": "other-servicesSMH4176.xlsx",
        "date": "2019-01-19",
        "uri": "op-infusion/oncology-treatment",
        "name": "OP infusion/oncology treatment",
        "url": "https://www.sharp.com/chargemaster/memorial/upload/SMH4176.xlsx"
    },
    {
        "hospital_id": "sharp-memorial-hospital",
        "filename": "other-servicesSMH4185.xlsx",
        "date": "2019-01-19",
        "uri": "pulmonary-rehabilitation",
        "name": "Pulmonary rehabilitation",
        "url": "https://www.sharp.com/chargemaster/memorial/upload/SMH4185.xlsx"
    },
    {
        "hospital_id": "sharp-memorial-hospital",
        "filename": "other-servicesSMH4180.xlsx",
        "date": "2019-01-19",
        "uri": "respiratory-therapy",
        "name": "Respiratory therapy",
        "url": "https://www.sharp.com/chargemaster/memorial/upload/SMH4180.xlsx"
    },
    {
        "hospital_id": "sharp-memorial-hospital",
        "filename": "other-servicesSMH4281.xlsx",
        "date": "2019-01-19",
        "uri": "senior-center",
        "name": "Senior Center",
        "url": "https://www.sharp.com/chargemaster/memorial/upload/SMH4281.xlsx"
    },
    {
        "hospital_id": "sharp-memorial-hospital",
        "filename": "other-servicesSMH4283.xlsx",
        "date": "2019-01-19",
        "uri": "senior-center-ii",
        "name": "Senior Center II",
        "url": "https://www.sharp.com/chargemaster/memorial/upload/SMH4283.xlsx"
    },
    {
        "hospital_id": "sharp-memorial-hospital",
        "filename": "cardiologySMH4116.xlsx",
        "date": "2019-01-19",
        "uri": "cardiac-rehabilitation",
        "name": "Cardiac rehabilitation",
        "url": "https://www.sharp.com/chargemaster/memorial/upload/SMH4116.xlsx"
    },
    {
        "hospital_id": "sharp-memorial-hospital",
        "filename": "cardiologySMH4440.xlsx",
        "date": "2019-01-19",
        "uri": "heart-catheterization-lab",
        "name": "Heart catheterization lab",
        "url": "https://www.sharp.com/chargemaster/memorial/upload/SMH4440.xlsx"
    },
    {
        "hospital_id": "sharp-memorial-hospital",
        "filename": "cardiologySMH4113.xlsx",
        "date": "2019-01-19",
        "uri": "noninvasive-cardiology",
        "name": "Noninvasive cardiology",
        "url": "https://www.sharp.com/chargemaster/memorial/upload/SMH4113.xlsx"
    },
    {
        "hospital_id": "sharp-memorial-hospital",
        "filename": "cardiologySMH4112.xlsx",
        "date": "2019-01-19",
        "uri": "vascular-lab",
        "name": "Vascular lab",
        "url": "https://www.sharp.com/chargemaster/memorial/upload/SMH4112.xlsx"
    },
    {
        "hospital_id": "sharp-memorial-hospital",
        "filename": "emergencySMH4231-2.xlsx",
        "date": "2019-01-19",
        "uri": "emergency",
        "name": "Emergency",
        "url": "https://www.sharp.com/chargemaster/memorial/upload/SMH4231-2.xlsx"
    },
    {
        "hospital_id": "sharp-memorial-hospital",
        "filename": "laboratorySMH4102.xlsx",
        "date": "2019-01-19",
        "uri": "blood-bank-products",
        "name": "Blood bank products",
        "url": "https://www.sharp.com/chargemaster/memorial/upload/SMH4102.xlsx"
    },
    {
        "hospital_id": "sharp-memorial-hospital",
        "filename": "laboratorySMH4065.xlsx",
        "date": "2019-01-19",
        "uri": "clinical-laboratory",
        "name": "Clinical laboratory",
        "url": "https://www.sharp.com/chargemaster/memorial/upload/SMH4065.xlsx"
    },
    {
        "hospital_id": "sharp-memorial-hospital",
        "filename": "laboratorySMH4068.xlsx",
        "date": "2019-01-19",
        "uri": "hla-laboratory",
        "name": "HLA laboratory",
        "url": "https://www.sharp.com/chargemaster/memorial/upload/SMH4068.xlsx"
    },
    {
        "hospital_id": "sharp-memorial-hospital",
        "filename": "laboratorySMH4063.xlsx",
        "date": "2019-01-19",
        "uri": "lab-copley-clinical",
        "name": "Lab Copley clinical",
        "url": "https://www.sharp.com/chargemaster/memorial/upload/SMH4063.xlsx"
    },
    {
        "hospital_id": "sharp-memorial-hospital",
        "filename": "laboratorySMH4062.xlsx",
        "date": "2019-01-19",
        "uri": "lab-copley-microbiology",
        "name": "Lab Copley microbiology",
        "url": "https://www.sharp.com/chargemaster/memorial/upload/SMH4062.xlsx"
    },
    {
        "hospital_id": "sharp-memorial-hospital",
        "filename": "laboratorySMH4066.xlsx",
        "date": "2019-01-19",
        "uri": "lab-send-out-tests",
        "name": "Lab send out tests",
        "url": "https://www.sharp.com/chargemaster/memorial/upload/SMH4066.xlsx"
    },
    {
        "hospital_id": "sharp-memorial-hospital",
        "filename": "laboratorySMH4070.xlsx",
        "date": "2019-01-19",
        "uri": "pathology",
        "name": "Pathology",
        "url": "https://www.sharp.com/chargemaster/memorial/upload/SMH4070.xlsx"
    },
    {
        "hospital_id": "sharp-memorial-hospital",
        "filename": "pharmacySMH4171.xlsx",
        "date": "2019-01-19",
        "uri": "pharmacy",
        "name": "Pharmacy",
        "url": "https://www.sharp.com/chargemaster/memorial/upload/SMH4171.xlsx"
    },
    {
        "hospital_id": "sharp-memorial-hospital",
        "filename": "radiologySMH4421.xlsx",
        "date": "2019-01-19",
        "uri": "computerized-tomography-(ct)-scanning",
        "name": "Computerized tomography (CT) scanning",
        "url": "https://www.sharp.com/chargemaster/memorial/upload/SMH4421.xlsx"
    },
    {
        "hospital_id": "sharp-memorial-hospital",
        "filename": "radiologySMH4142.xlsx",
        "date": "2019-01-19",
        "uri": "general-radiology",
        "name": "General radiology",
        "url": "https://www.sharp.com/chargemaster/memorial/upload/SMH4142.xlsx"
    },
    {
        "hospital_id": "sharp-memorial-hospital",
        "filename": "radiologySMH4165.xlsx",
        "date": "2019-01-19",
        "uri": "imaging-offices",
        "name": "Imaging offices",
        "url": "https://www.sharp.com/chargemaster/memorial/upload/SMH4165.xlsx"
    },
    {
        "hospital_id": "sharp-memorial-hospital",
        "filename": "radiologySMH4425.xlsx",
        "date": "2019-01-19",
        "uri": "magnetic-resonance-imaging-(mri)",
        "name": "Magnetic resonance imaging (MRI)",
        "url": "https://www.sharp.com/chargemaster/memorial/upload/SMH4425.xlsx"
    },
    {
        "hospital_id": "sharp-memorial-hospital",
        "filename": "radiologySMH4160.xlsx",
        "date": "2019-01-19",
        "uri": "nuclear-medicine",
        "name": "Nuclear medicine",
        "url": "https://www.sharp.com/chargemaster/memorial/upload/SMH4160.xlsx"
    },
    {
        "hospital_id": "sharp-memorial-hospital",
        "filename": "radiologySMH4162.xlsx",
        "date": "2019-01-19",
        "uri": "positron-emission-tomography-(pet)",
        "name": "Positron emission tomography (PET)",
        "url": "https://www.sharp.com/chargemaster/memorial/upload/SMH4162.xlsx"
    },
    {
        "hospital_id": "sharp-memorial-hospital",
        "filename": "radiologySMH4152.xlsx",
        "date": "2019-01-19",
        "uri": "radiation-oncology-treatment",
        "name": "Radiation oncology treatment",
        "url": "https://www.sharp.com/chargemaster/memorial/upload/SMH4152.xlsx"
    },
    {
        "hospital_id": "sharp-memorial-hospital",
        "filename": "radiologySMH4144.xlsx",
        "date": "2019-01-19",
        "uri": "radiology-special-procedure",
        "name": "Radiology special procedure",
        "url": "https://www.sharp.com/chargemaster/memorial/upload/SMH4144.xlsx"
    },
    {
        "hospital_id": "sharp-memorial-hospital",
        "filename": "radiologySMH4143.xlsx",
        "date": "2019-01-19",
        "uri": "ultrasound",
        "name": "Ultrasound",
        "url": "https://www.sharp.com/chargemaster/memorial/upload/SMH4143.xlsx"
    },
    {
        "hospital_id": "sharp-memorial-hospital",
        "filename": "rehabilitationSMH4211.xlsx",
        "date": "2019-01-19",
        "uri": "occupational-therapy-treatment",
        "name": "Occupational therapy treatment",
        "url": "https://www.sharp.com/chargemaster/memorial/upload/SMH4211.xlsx"
    },
    {
        "hospital_id": "sharp-memorial-hospital",
        "filename": "rehabilitationSMH4411.xlsx",
        "date": "2019-01-19",
        "uri": "outpatient-psychiatric-services",
        "name": "Outpatient psychiatric services",
        "url": "https://www.sharp.com/chargemaster/memorial/upload/SMH4411.xlsx"
    },
    {
        "hospital_id": "sharp-memorial-hospital",
        "filename": "rehabilitationSMH4200.xlsx",
        "date": "2019-01-19",
        "uri": "physical-therapy-clinic",
        "name": "Physical therapy clinic",
        "url": "https://www.sharp.com/chargemaster/memorial/upload/SMH4200.xlsx"
    },
    {
        "hospital_id": "sharp-memorial-hospital",
        "filename": "rehabilitationSMH4201.xlsx",
        "date": "2019-01-19",
        "uri": "physical-therapy-general-treatment",
        "name": "Physical therapy general treatment",
        "url": "https://www.sharp.com/chargemaster/memorial/upload/SMH4201.xlsx"
    },
    {
        "hospital_id": "sharp-memorial-hospital",
        "filename": "rehabilitationSMH4280.xlsx",
        "date": "2019-01-19",
        "uri": "rehab-clinic",
        "name": "Rehab clinic",
        "url": "https://www.sharp.com/chargemaster/memorial/upload/SMH4280.xlsx"
    },
    {
        "hospital_id": "sharp-memorial-hospital",
        "filename": "rehabilitationSMH4413.xlsx",
        "date": "2019-01-19",
        "uri": "rehabilitation-pain-program",
        "name": "Rehabilitation pain program",
        "url": "https://www.sharp.com/chargemaster/memorial/upload/SMH4413.xlsx"
    },
    {
        "hospital_id": "sharp-memorial-hospital",
        "filename": "rehabilitationSMH4414.xlsx",
        "date": "2019-01-19",
        "uri": "rehabilitation-day-treatment",
        "name": "Rehabilitation day treatment",
        "url": "https://www.sharp.com/chargemaster/memorial/upload/SMH4414.xlsx"
    },
    {
        "hospital_id": "sharp-memorial-hospital",
        "filename": "rehabilitationSMH4221.xlsx",
        "date": "2019-01-19",
        "uri": "speech-therapy",
        "name": "Speech therapy",
        "url": "https://www.sharp.com/chargemaster/memorial/upload/SMH4221.xlsx"
    },
    {
        "hospital_id": "sharp-memorial-hospital",
        "filename": "womens-servicesSMH4018.xlsx",
        "date": "2019-01-19",
        "uri": "antenatal-testing",
        "name": "Antenatal testing",
        "url": "https://www.sharp.com/chargemaster/memorial/upload/SMH4018.xlsx"
    },
    {
        "hospital_id": "sharp-memorial-hospital",
        "filename": "womens-servicesSMH4010.xlsx",
        "date": "2019-01-19",
        "uri": "infant-clinic",
        "name": "Infant clinic",
        "url": "https://www.sharp.com/chargemaster/memorial/upload/SMH4010.xlsx"
    },
    {
        "hospital_id": "sharp-memorial-hospital",
        "filename": "womens-servicesSMH4011.xlsx",
        "date": "2019-01-19",
        "uri": "labor-and-delivery",
        "name": "Labor and delivery",
        "url": "https://www.sharp.com/chargemaster/memorial/upload/SMH4011.xlsx"
    },
    {
        "hospital_id": "sharp-memorial-hospital",
        "filename": "womens-servicesSMH4019.xlsx",
        "date": "2019-01-19",
        "uri": "lactation",
        "name": "Lactation",
        "url": "https://www.sharp.com/chargemaster/memorial/upload/SMH4019.xlsx"
    },
    {
        "hospital_id": "sharp-memorial-hospital",
        "filename": "womens-servicesSMH4012.xlsx",
        "date": "2019-01-19",
        "uri": "surgical-gynecology",
        "name": "Surgical gynecology",
        "url": "https://www.sharp.com/chargemaster/memorial/upload/SMH4012.xlsx"
    },
    {
        "hospital_id": "sharp-memorial-hospital",
        "filename": "womens-servicesSMH4016.xlsx",
        "date": "2019-01-19",
        "uri": "women's-center-recovery",
        "name": "Women's center recovery",
        "url": "https://www.sharp.com/chargemaster/memorial/upload/SMH4016.xlsx"
    },
    {
        "hospital_id": "sharp-memorial-hospital",
        "filename": "womens-servicesSMH4014.xlsx",
        "date": "2019-01-19",
        "uri": "women's-triage",
        "name": "Women's triage",
        "url": "https://www.sharp.com/chargemaster/memorial/upload/SMH4014.xlsx"
    },
    {
        "hospital_id": "sharp-memorial-hospital",
        "filename": "behavioral-healthSMH4338.xlsx",
        "date": "2019-01-19",
        "uri": "child/adolescent",
        "name": "Child/adolescent",
        "url": "https://www.sharp.com/chargemaster/memorial/upload/SMH4338.xlsx"
    },
    {
        "hospital_id": "sharp-memorial-hospital",
        "filename": "behavioral-healthSMH4349.xlsx",
        "date": "2019-01-19",
        "uri": "dual-recovery-program",
        "name": "Dual recovery program",
        "url": "https://www.sharp.com/chargemaster/memorial/upload/SMH4349.xlsx"
    },
    {
        "hospital_id": "sharp-memorial-hospital",
        "filename": "behavioral-healthSMH4354.xlsx",
        "date": "2019-01-19",
        "uri": "eating-disorders",
        "name": "Eating disorders",
        "url": "https://www.sharp.com/chargemaster/memorial/upload/SMH4354.xlsx"
    },
    {
        "hospital_id": "sharp-memorial-hospital",
        "filename": "behavioral-healthSMH4340.xlsx",
        "date": "2019-01-19",
        "uri": "kearny-mesa",
        "name": "Kearny Mesa",
        "url": "https://www.sharp.com/chargemaster/memorial/upload/SMH4340.xlsx"
    },
    {
        "hospital_id": "sharp-memorial-hospital",
        "filename": "behavioral-healthSMH4341.xlsx",
        "date": "2019-01-19",
        "uri": "mesa-vista-east",
        "name": "Mesa Vista East",
        "url": "https://www.sharp.com/chargemaster/memorial/upload/SMH4341.xlsx"
    },
    {
        "hospital_id": "sharp-memorial-hospital",
        "filename": "behavioral-healthSMH4342.xlsx",
        "date": "2019-01-19",
        "uri": "mesa-vista-east-ii",
        "name": "Mesa Vista East II",
        "url": "https://www.sharp.com/chargemaster/memorial/upload/SMH4342.xlsx"
    },
    {
        "hospital_id": "sharp-memorial-hospital",
        "filename": "behavioral-healthSMH4337.xlsx",
        "date": "2019-01-19",
        "uri": "mesa-vista-east-adolescent",
        "name": "Mesa Vista East adolescent",
        "url": "https://www.sharp.com/chargemaster/memorial/upload/SMH4337.xlsx"
    },
    {
        "hospital_id": "sharp-memorial-hospital",
        "filename": "behavioral-healthSMH4348.xlsx",
        "date": "2019-01-19",
        "uri": "outpatient-program",
        "name": "Outpatient program",
        "url": "https://www.sharp.com/chargemaster/memorial/upload/SMH4348.xlsx"
    },
    {
        "hospital_id": "sharp-memorial-hospital",
        "filename": "behavioral-healthSMH4347.xlsx",
        "date": "2019-01-19",
        "uri": "partial-hospitalization",
        "name": "Partial hospitalization",
        "url": "https://www.sharp.com/chargemaster/memorial/upload/SMH4347.xlsx"
    },
    {
        "hospital_id": "sharp-memorial-hospital",
        "filename": "behavioral-healthSMH4352.xlsx",
        "date": "2019-01-19",
        "uri": "senior-program",
        "name": "Senior program",
        "url": "https://www.sharp.com/chargemaster/memorial/upload/SMH4352.xlsx"
    },
    {
        "hospital_id": "sharp-memorial-hospital",
        "filename": "behavioral-healthSMH4339.xlsx",
        "date": "2019-01-19",
        "uri": "special-services",
        "name": "Special services",
        "url": "https://www.sharp.com/chargemaster/memorial/upload/SMH4339.xlsx"
    },
    {
        "hospital_id": "sharp-memorial-hospital",
        "filename": "behavioral-healthSMH4346.xlsx",
        "date": "2019-01-19",
        "uri": "university-heights",
        "name": "University Heights",
        "url": "https://www.sharp.com/chargemaster/memorial/upload/SMH4346.xlsx"
    },
    {
        "hospital_id": "sharp-memorial-hospital",
        "filename": "acute-care-room-boardSMH3347.xlsx",
        "date": "2019-01-19",
        "uri": "behavioral-health-child/adolescent-unit",
        "name": "Behavioral health child/adolescent unit",
        "url": "https://www.sharp.com/chargemaster/memorial/upload/SMH3347.xlsx"
    },
    {
        "hospital_id": "sharp-memorial-hospital",
        "filename": "acute-care-room-boardSMH3344.xlsx",
        "date": "2019-01-19",
        "uri": "behavioral-health-detox/rehab-unit",
        "name": "Behavioral health detox/rehab unit",
        "url": "https://www.sharp.com/chargemaster/memorial/upload/SMH3344.xlsx"
    },
    {
        "hospital_id": "sharp-memorial-hospital",
        "filename": "acute-care-room-boardSMH3345.xlsx",
        "date": "2019-01-19",
        "uri": "behavioral-health-intensive-care-unit",
        "name": "Behavioral health intensive care unit",
        "url": "https://www.sharp.com/chargemaster/memorial/upload/SMH3345.xlsx"
    },
    {
        "hospital_id": "sharp-memorial-hospital",
        "filename": "acute-care-room-boardSMH3348.xlsx",
        "date": "2019-01-19",
        "uri": "behavioral-health-locked-unit-3342",
        "name": "Behavioral health locked unit 3342",
        "url": "https://www.sharp.com/chargemaster/memorial/upload/SMH3348.xlsx"
    },
    {
        "hospital_id": "sharp-memorial-hospital",
        "filename": "acute-care-room-boardSMH3342.xlsx",
        "date": "2019-01-19",
        "uri": "behavioral-health-locked-unit-3343",
        "name": "Behavioral health locked unit 3343",
        "url": "https://www.sharp.com/chargemaster/memorial/upload/SMH3342.xlsx"
    },
    {
        "hospital_id": "sharp-memorial-hospital",
        "filename": "acute-care-room-boardSMH3176.xlsx",
        "date": "2019-01-19",
        "uri": "gyn/ms-acute",
        "name": "GYN/MS acute",
        "url": "https://www.sharp.com/chargemaster/memorial/upload/SMH3176.xlsx"
    },
    {
        "hospital_id": "sharp-memorial-hospital",
        "filename": "acute-care-room-boardSMH3341.xlsx",
        "date": "2019-01-19",
        "uri": "inpatient-behavioral-health-unit",
        "name": "Inpatient behavioral health unit",
        "url": "https://www.sharp.com/chargemaster/memorial/upload/SMH3341.xlsx"
    },
    {
        "hospital_id": "sharp-memorial-hospital",
        "filename": "acute-care-room-boardSMH3201.xlsx",
        "date": "2019-01-19",
        "uri": "inpatient-rehabilitation-unit",
        "name": "Inpatient rehabilitation unit",
        "url": "https://www.sharp.com/chargemaster/memorial/upload/SMH3201.xlsx"
    },
    {
        "hospital_id": "sharp-memorial-hospital",
        "filename": "acute-care-room-boardSMH3030.xlsx",
        "date": "2019-01-19",
        "uri": "intermediate-care-unit-3030",
        "name": "Intermediate care unit 3030",
        "url": "https://www.sharp.com/chargemaster/memorial/upload/SMH3030.xlsx"
    },
    {
        "hospital_id": "sharp-memorial-hospital",
        "filename": "acute-care-room-boardSMH3031.xlsx",
        "date": "2019-01-19",
        "uri": "intermediate-care-unit-3031",
        "name": "Intermediate care unit 3031",
        "url": "https://www.sharp.com/chargemaster/memorial/upload/SMH3031.xlsx"
    },
    {
        "hospital_id": "sharp-memorial-hospital",
        "filename": "acute-care-room-boardSMH3032.xlsx",
        "date": "2019-01-19",
        "uri": "intermediate-care-unit-3032",
        "name": "Intermediate care unit 3032",
        "url": "https://www.sharp.com/chargemaster/memorial/upload/SMH3032.xlsx"
    },
    {
        "hospital_id": "sharp-memorial-hospital",
        "filename": "acute-care-room-boardSMH3033.xlsx",
        "date": "2019-01-19",
        "uri": "intermediate-care-unit-3033",
        "name": "Intermediate care unit 3033",
        "url": "https://www.sharp.com/chargemaster/memorial/upload/SMH3033.xlsx"
    },
    {
        "hospital_id": "sharp-memorial-hospital",
        "filename": "acute-care-room-boardSMH3082.xlsx",
        "date": "2019-01-19",
        "uri": "intermediate-care-unit-3082",
        "name": "Intermediate care unit 3082",
        "url": "https://www.sharp.com/chargemaster/memorial/upload/SMH3082.xlsx"
    },
    {
        "hospital_id": "sharp-memorial-hospital",
        "filename": "acute-care-room-boardSMH3161.xlsx",
        "date": "2019-01-19",
        "uri": "maternal/infant-services",
        "name": "Maternal/infant services",
        "url": "https://www.sharp.com/chargemaster/memorial/upload/SMH3161.xlsx"
    },
    {
        "hospital_id": "sharp-memorial-hospital",
        "filename": "acute-care-room-boardSMH3420.xlsx",
        "date": "2019-01-19",
        "uri": "sharp-mcdonald-center-chemical-dependency-unit",
        "name": "Sharp McDonald Center chemical dependency unit",
        "url": "https://www.sharp.com/chargemaster/memorial/upload/SMH3420.xlsx"
    },
    {
        "hospital_id": "sharp-memorial-hospital",
        "filename": "acute-care-room-boardSMH3011.xlsx",
        "date": "2019-01-19",
        "uri": "medical-intensive-care-unit-3011",
        "name": "Medical intensive care unit 3011",
        "url": "https://www.sharp.com/chargemaster/memorial/upload/SMH3011.xlsx"
    },
    {
        "hospital_id": "sharp-memorial-hospital",
        "filename": "acute-care-room-boardSMH3015.xlsx",
        "date": "2019-01-19",
        "uri": "medical-intensive-care-unit-3015",
        "name": "Medical intensive care unit 3015",
        "url": "https://www.sharp.com/chargemaster/memorial/upload/SMH3015.xlsx"
    },
    {
        "hospital_id": "sharp-memorial-hospital",
        "filename": "acute-care-room-boardSMH3084.xlsx",
        "date": "2019-01-19",
        "uri": "medical/surgical-3084",
        "name": "Medical/surgical 3084",
        "url": "https://www.sharp.com/chargemaster/memorial/upload/SMH3084.xlsx"
    },
    {
        "hospital_id": "sharp-memorial-hospital",
        "filename": "acute-care-room-boardSMH3085.xlsx",
        "date": "2019-01-19",
        "uri": "medical/surgical-3085",
        "name": "Medical/surgical 3085",
        "url": "https://www.sharp.com/chargemaster/memorial/upload/SMH3085.xlsx"
    },
    {
        "hospital_id": "sharp-memorial-hospital",
        "filename": "acute-care-room-boardSMH3087.xlsx",
        "date": "2019-01-19",
        "uri": "medical/surgical-3087",
        "name": "Medical/surgical 3087",
        "url": "https://www.sharp.com/chargemaster/memorial/upload/SMH3087.xlsx"
    },
    {
        "hospital_id": "sharp-memorial-hospital",
        "filename": "acute-care-room-boardSMH3089.xlsx",
        "date": "2019-01-19",
        "uri": "medical/surgical-3089",
        "name": "Medical/surgical 3089",
        "url": "https://www.sharp.com/chargemaster/memorial/upload/SMH3089.xlsx"
    },
    {
        "hospital_id": "sharp-memorial-hospital",
        "filename": "acute-care-room-boardSMH3181.xlsx",
        "date": "2019-01-19",
        "uri": "medical/surgical-3181",
        "name": "Medical/surgical 3181",
        "url": "https://www.sharp.com/chargemaster/memorial/upload/SMH3181.xlsx"
    },
    {
        "hospital_id": "sharp-memorial-hospital",
        "filename": "acute-care-room-boardSMH3360.xlsx",
        "date": "2019-01-19",
        "uri": "medical/surgical-3360",
        "name": "Medical/surgical 3360",
        "url": "https://www.sharp.com/chargemaster/memorial/upload/SMH3360.xlsx"
    },
    {
        "hospital_id": "sharp-memorial-hospital",
        "filename": "acute-care-room-boardSMH3172.xlsx",
        "date": "2019-01-19",
        "uri": "neonatal-intensive-care-unit",
        "name": "Neonatal intensive care unit",
        "url": "https://www.sharp.com/chargemaster/memorial/upload/SMH3172.xlsx"
    },
    {
        "hospital_id": "sharp-memorial-hospital",
        "filename": "acute-care-room-boardSMH3171.xlsx",
        "date": "2019-01-19",
        "uri": "nursery",
        "name": "Nursery",
        "url": "https://www.sharp.com/chargemaster/memorial/upload/SMH3171.xlsx"
    },
    {
        "hospital_id": "sharp-memorial-hospital",
        "filename": "acute-care-room-boardSMH3163.xlsx",
        "date": "2019-01-19",
        "uri": "obgyn-acute-care-unit",
        "name": "OBGYN acute care unit",
        "url": "https://www.sharp.com/chargemaster/memorial/upload/SMH3163.xlsx"
    },
    {
        "hospital_id": "sharp-memorial-hospital",
        "filename": "acute-care-room-boardSMH3164.xlsx",
        "date": "2019-01-19",
        "uri": "ob-special-care/mis",
        "name": "OB special care/MIS",
        "url": "https://www.sharp.com/chargemaster/memorial/upload/SMH3164.xlsx"
    },
    {
        "hospital_id": "sharp-memorial-hospital",
        "filename": "acute-care-room-boardSMH3162.xlsx",
        "date": "2019-01-19",
        "uri": "obstetrical-special-services",
        "name": "Obstetrical special services",
        "url": "https://www.sharp.com/chargemaster/memorial/upload/SMH3162.xlsx"
    },
    {
        "hospital_id": "sharp-memorial-hospital",
        "filename": "acute-care-room-boardSMH3346.xlsx",
        "date": "2019-01-19",
        "uri": "older-adult-psychiatric-unit",
        "name": "Older adult psychiatric unit",
        "url": "https://www.sharp.com/chargemaster/memorial/upload/SMH3346.xlsx"
    },
    {
        "hospital_id": "sharp-memorial-hospital",
        "filename": "acute-care-room-boardSMH3012.xlsx",
        "date": "2019-01-19",
        "uri": "surgical-intensive-care-unit",
        "name": "Surgical intensive care unit",
        "url": "https://www.sharp.com/chargemaster/memorial/upload/SMH3012.xlsx"
    },
    {
        "hospital_id": "sharp-memorial-hospital",
        "filename": "standard-charges2018-DRG-Files-for-Sharp-update-2019-01-04-com.xlsx",
        "date": "2019-01-19",
        "uri": "standard-charges-for-2019",
        "name": "Standard Charges for 2019",
        "url": "https://www.sharp.com/chargemaster/upload/2018-DRG-Files-for-Sharp-update-2019-01-04-com.xlsx"
    },
    {
        "hospital_id": "sharp-memorial-hospital",
        "filename": "suppliesSMH4052.xlsx",
        "date": "2019-01-19",
        "uri": "central-supply",
        "name": "Central supply",
        "url": "https://www.sharp.com/chargemaster/memorial/upload/SMH4052.xlsx"
    },
    {
        "hospital_id": "sharp-memorial-hospital",
        "filename": "surgerySMH4041.xlsx",
        "date": "2019-01-19",
        "uri": "anesthesiology",
        "name": "Anesthesiology",
        "url": "https://www.sharp.com/chargemaster/memorial/upload/SMH4041.xlsx"
    },
    {
        "hospital_id": "sharp-memorial-hospital",
        "filename": "surgerySMH4231.xlsx",
        "date": "2019-01-19",
        "uri": "endoscopy-services",
        "name": "Endoscopy services",
        "url": "https://www.sharp.com/chargemaster/memorial/upload/SMH4231.xlsx"
    },
    {
        "hospital_id": "sharp-memorial-hospital",
        "filename": "surgerySMH4022.xlsx",
        "date": "2019-01-19",
        "uri": "heart-transplant",
        "name": "Heart transplant",
        "url": "https://www.sharp.com/chargemaster/memorial/upload/SMH4022.xlsx"
    },
    {
        "hospital_id": "sharp-memorial-hospital",
        "filename": "surgerySMH4028.xlsx",
        "date": "2019-01-19",
        "uri": "kidney-transplant",
        "name": "Kidney transplant",
        "url": "https://www.sharp.com/chargemaster/memorial/upload/SMH4028.xlsx"
    },
    {
        "hospital_id": "sharp-memorial-hospital",
        "filename": "surgerySMH4426.xlsx",
        "date": "2019-01-19",
        "uri": "mechanical-assist-program",
        "name": "Mechanical assist program",
        "url": "https://www.sharp.com/chargemaster/memorial/upload/SMH4426.xlsx"
    },
    {
        "hospital_id": "sharp-memorial-hospital",
        "filename": "surgerySMH4035.xlsx",
        "date": "2019-01-19",
        "uri": "outpatient-surgical-center",
        "name": "Outpatient Surgical Center",
        "url": "https://www.sharp.com/chargemaster/memorial/upload/SMH4035.xlsx"
    },
    {
        "hospital_id": "sharp-memorial-hospital",
        "filename": "surgerySMH4021.xlsx",
        "date": "2019-01-19",
        "uri": "surgery/operating-room",
        "name": "Surgery/operating room",
        "url": "https://www.sharp.com/chargemaster/memorial/upload/SMH4021.xlsx"
    },
    {
        "hospital_id": "sharp-memorial-hospital",
        "filename": "surgerySMH4029.xlsx",
        "date": "2019-01-19",
        "uri": "surgery-recovery",
        "name": "Surgery recovery",
        "url": "https://www.sharp.com/chargemaster/memorial/upload/SMH4029.xlsx"
    },
    {
        "hospital_id": "sharp-memorial-hospital",
        "filename": "surgerySMH4052-2.xlsx",
        "date": "2019-01-19",
        "uri": "surgery-supplies",
        "name": "Surgery supplies",
        "url": "https://www.sharp.com/chargemaster/memorial/upload/SMH4052-2.xlsx"
    },
    {
        "hospital_id": "sharp-memorial-hospital",
        "filename": "surgerySMH4175.xlsx",
        "date": "2019-01-19",
        "uri": "vascular-access-service",
        "name": "Vascular access service",
        "url": "https://www.sharp.com/chargemaster/memorial/upload/SMH4175.xlsx"
    },
    {
        "hospital_id": "sharp-memorial-hospital",
        "filename": "other-servicesSMH4801.xlsx",
        "date": "2019-01-19",
        "uri": "audiology",
        "name": "Audiology",
        "url": "https://www.sharp.com/chargemaster/memorial/upload/SMH4801.xlsx"
    },
    {
        "hospital_id": "sharp-memorial-hospital",
        "filename": "other-servicesSMH4417.xlsx",
        "date": "2019-01-19",
        "uri": "diabetes",
        "name": "Diabetes",
        "url": "https://www.sharp.com/chargemaster/memorial/upload/SMH4417.xlsx"
    },
    {
        "hospital_id": "sharp-memorial-hospital",
        "filename": "other-servicesSMH4190.xlsx",
        "date": "2019-01-19",
        "uri": "dialysis",
        "name": "Dialysis",
        "url": "https://www.sharp.com/chargemaster/memorial/upload/SMH4190.xlsx"
    },
    {
        "hospital_id": "sharp-memorial-hospital",
        "filename": "other-servicesSMH4418.xlsx",
        "date": "2019-01-19",
        "uri": "electroconvulsive-therapy",
        "name": "Electroconvulsive therapy",
        "url": "https://www.sharp.com/chargemaster/memorial/upload/SMH4418.xlsx"
    },
    {
        "hospital_id": "sharp-memorial-hospital",
        "filename": "other-servicesSMH4130.xlsx",
        "date": "2019-01-19",
        "uri": "electroencephalography-(eeg)",
        "name": "Electroencephalography (EEG)",
        "url": "https://www.sharp.com/chargemaster/memorial/upload/SMH4130.xlsx"
    },
    {
        "hospital_id": "sharp-memorial-hospital",
        "filename": "other-servicesSMH4091.xlsx",
        "date": "2019-01-19",
        "uri": "endoscopy-services",
        "name": "Endoscopy services",
        "url": "https://www.sharp.com/chargemaster/memorial/upload/SMH4091.xlsx"
    },
    {
        "hospital_id": "sharp-memorial-hospital",
        "filename": "other-servicesSMH4076.xlsx",
        "date": "2019-01-19",
        "uri": "executive-health-services",
        "name": "Executive health services",
        "url": "https://www.sharp.com/chargemaster/memorial/upload/SMH4076.xlsx"
    },
    {
        "hospital_id": "sharp-memorial-hospital",
        "filename": "other-servicesSMH4215.xlsx",
        "date": "2019-01-19",
        "uri": "lymphedema",
        "name": "Lymphedema",
        "url": "https://www.sharp.com/chargemaster/memorial/upload/SMH4215.xlsx"
    },
    {
        "hospital_id": "sharp-memorial-hospital",
        "filename": "other-servicesSMH4332.xlsx",
        "date": "2019-01-19",
        "uri": "nutrition-services",
        "name": "Nutrition services",
        "url": "https://www.sharp.com/chargemaster/memorial/upload/SMH4332.xlsx"
    },
    {
        "hospital_id": "sharp-memorial-hospital",
        "filename": "other-servicesSMH4264.xlsx",
        "date": "2019-01-19",
        "uri": "ophthalmology-clinic",
        "name": "Ophthalmology clinic",
        "url": "https://www.sharp.com/chargemaster/memorial/upload/SMH4264.xlsx"
    },
    {
        "hospital_id": "sharp-memorial-hospital",
        "filename": "other-servicesSMH4176.xlsx",
        "date": "2019-01-19",
        "uri": "op-infusion/oncology-treatment",
        "name": "OP infusion/oncology treatment",
        "url": "https://www.sharp.com/chargemaster/memorial/upload/SMH4176.xlsx"
    },
    {
        "hospital_id": "sharp-memorial-hospital",
        "filename": "other-servicesSMH4185.xlsx",
        "date": "2019-01-19",
        "uri": "pulmonary-rehabilitation",
        "name": "Pulmonary rehabilitation",
        "url": "https://www.sharp.com/chargemaster/memorial/upload/SMH4185.xlsx"
    },
    {
        "hospital_id": "sharp-memorial-hospital",
        "filename": "other-servicesSMH4180.xlsx",
        "date": "2019-01-19",
        "uri": "respiratory-therapy",
        "name": "Respiratory therapy",
        "url": "https://www.sharp.com/chargemaster/memorial/upload/SMH4180.xlsx"
    },
    {
        "hospital_id": "sharp-memorial-hospital",
        "filename": "other-servicesSMH4281.xlsx",
        "date": "2019-01-19",
        "uri": "senior-center",
        "name": "Senior Center",
        "url": "https://www.sharp.com/chargemaster/memorial/upload/SMH4281.xlsx"
    },
    {
        "hospital_id": "sharp-memorial-hospital",
        "filename": "other-servicesSMH4283.xlsx",
        "date": "2019-01-19",
        "uri": "senior-center-ii",
        "name": "Senior Center II",
        "url": "https://www.sharp.com/chargemaster/memorial/upload/SMH4283.xlsx"
    },
    {
        "hospital_id": "sharp-memorial-hospital",
        "filename": "cardiologySMH4116.xlsx",
        "date": "2019-01-19",
        "uri": "cardiac-rehabilitation",
        "name": "Cardiac rehabilitation",
        "url": "https://www.sharp.com/chargemaster/memorial/upload/SMH4116.xlsx"
    },
    {
        "hospital_id": "sharp-memorial-hospital",
        "filename": "cardiologySMH4440.xlsx",
        "date": "2019-01-19",
        "uri": "heart-catheterization-lab",
        "name": "Heart catheterization lab",
        "url": "https://www.sharp.com/chargemaster/memorial/upload/SMH4440.xlsx"
    },
    {
        "hospital_id": "sharp-memorial-hospital",
        "filename": "cardiologySMH4113.xlsx",
        "date": "2019-01-19",
        "uri": "noninvasive-cardiology",
        "name": "Noninvasive cardiology",
        "url": "https://www.sharp.com/chargemaster/memorial/upload/SMH4113.xlsx"
    },
    {
        "hospital_id": "sharp-memorial-hospital",
        "filename": "cardiologySMH4112.xlsx",
        "date": "2019-01-19",
        "uri": "vascular-lab",
        "name": "Vascular lab",
        "url": "https://www.sharp.com/chargemaster/memorial/upload/SMH4112.xlsx"
    },
    {
        "hospital_id": "sharp-memorial-hospital",
        "filename": "emergencySMH4231-2.xlsx",
        "date": "2019-01-19",
        "uri": "emergency",
        "name": "Emergency",
        "url": "https://www.sharp.com/chargemaster/memorial/upload/SMH4231-2.xlsx"
    },
    {
        "hospital_id": "sharp-memorial-hospital",
        "filename": "laboratorySMH4102.xlsx",
        "date": "2019-01-19",
        "uri": "blood-bank-products",
        "name": "Blood bank products",
        "url": "https://www.sharp.com/chargemaster/memorial/upload/SMH4102.xlsx"
    },
    {
        "hospital_id": "sharp-memorial-hospital",
        "filename": "laboratorySMH4065.xlsx",
        "date": "2019-01-19",
        "uri": "clinical-laboratory",
        "name": "Clinical laboratory",
        "url": "https://www.sharp.com/chargemaster/memorial/upload/SMH4065.xlsx"
    },
    {
        "hospital_id": "sharp-memorial-hospital",
        "filename": "laboratorySMH4068.xlsx",
        "date": "2019-01-19",
        "uri": "hla-laboratory",
        "name": "HLA laboratory",
        "url": "https://www.sharp.com/chargemaster/memorial/upload/SMH4068.xlsx"
    },
    {
        "hospital_id": "sharp-memorial-hospital",
        "filename": "laboratorySMH4063.xlsx",
        "date": "2019-01-19",
        "uri": "lab-copley-clinical",
        "name": "Lab Copley clinical",
        "url": "https://www.sharp.com/chargemaster/memorial/upload/SMH4063.xlsx"
    },
    {
        "hospital_id": "sharp-memorial-hospital",
        "filename": "laboratorySMH4062.xlsx",
        "date": "2019-01-19",
        "uri": "lab-copley-microbiology",
        "name": "Lab Copley microbiology",
        "url": "https://www.sharp.com/chargemaster/memorial/upload/SMH4062.xlsx"
    },
    {
        "hospital_id": "sharp-memorial-hospital",
        "filename": "laboratorySMH4066.xlsx",
        "date": "2019-01-19",
        "uri": "lab-send-out-tests",
        "name": "Lab send out tests",
        "url": "https://www.sharp.com/chargemaster/memorial/upload/SMH4066.xlsx"
    },
    {
        "hospital_id": "sharp-memorial-hospital",
        "filename": "laboratorySMH4070.xlsx",
        "date": "2019-01-19",
        "uri": "pathology",
        "name": "Pathology",
        "url": "https://www.sharp.com/chargemaster/memorial/upload/SMH4070.xlsx"
    },
    {
        "hospital_id": "sharp-memorial-hospital",
        "filename": "pharmacySMH4171.xlsx",
        "date": "2019-01-19",
        "uri": "pharmacy",
        "name": "Pharmacy",
        "url": "https://www.sharp.com/chargemaster/memorial/upload/SMH4171.xlsx"
    },
    {
        "hospital_id": "sharp-memorial-hospital",
        "filename": "radiologySMH4421.xlsx",
        "date": "2019-01-19",
        "uri": "computerized-tomography-(ct)-scanning",
        "name": "Computerized tomography (CT) scanning",
        "url": "https://www.sharp.com/chargemaster/memorial/upload/SMH4421.xlsx"
    },
    {
        "hospital_id": "sharp-memorial-hospital",
        "filename": "radiologySMH4142.xlsx",
        "date": "2019-01-19",
        "uri": "general-radiology",
        "name": "General radiology",
        "url": "https://www.sharp.com/chargemaster/memorial/upload/SMH4142.xlsx"
    },
    {
        "hospital_id": "sharp-memorial-hospital",
        "filename": "radiologySMH4165.xlsx",
        "date": "2019-01-19",
        "uri": "imaging-offices",
        "name": "Imaging offices",
        "url": "https://www.sharp.com/chargemaster/memorial/upload/SMH4165.xlsx"
    },
    {
        "hospital_id": "sharp-memorial-hospital",
        "filename": "radiologySMH4425.xlsx",
        "date": "2019-01-19",
        "uri": "magnetic-resonance-imaging-(mri)",
        "name": "Magnetic resonance imaging (MRI)",
        "url": "https://www.sharp.com/chargemaster/memorial/upload/SMH4425.xlsx"
    },
    {
        "hospital_id": "sharp-memorial-hospital",
        "filename": "radiologySMH4160.xlsx",
        "date": "2019-01-19",
        "uri": "nuclear-medicine",
        "name": "Nuclear medicine",
        "url": "https://www.sharp.com/chargemaster/memorial/upload/SMH4160.xlsx"
    },
    {
        "hospital_id": "sharp-memorial-hospital",
        "filename": "radiologySMH4162.xlsx",
        "date": "2019-01-19",
        "uri": "positron-emission-tomography-(pet)",
        "name": "Positron emission tomography (PET)",
        "url": "https://www.sharp.com/chargemaster/memorial/upload/SMH4162.xlsx"
    },
    {
        "hospital_id": "sharp-memorial-hospital",
        "filename": "radiologySMH4152.xlsx",
        "date": "2019-01-19",
        "uri": "radiation-oncology-treatment",
        "name": "Radiation oncology treatment",
        "url": "https://www.sharp.com/chargemaster/memorial/upload/SMH4152.xlsx"
    },
    {
        "hospital_id": "sharp-memorial-hospital",
        "filename": "radiologySMH4144.xlsx",
        "date": "2019-01-19",
        "uri": "radiology-special-procedure",
        "name": "Radiology special procedure",
        "url": "https://www.sharp.com/chargemaster/memorial/upload/SMH4144.xlsx"
    },
    {
        "hospital_id": "sharp-memorial-hospital",
        "filename": "radiologySMH4143.xlsx",
        "date": "2019-01-19",
        "uri": "ultrasound",
        "name": "Ultrasound",
        "url": "https://www.sharp.com/chargemaster/memorial/upload/SMH4143.xlsx"
    },
    {
        "hospital_id": "sharp-memorial-hospital",
        "filename": "rehabilitationSMH4211.xlsx",
        "date": "2019-01-19",
        "uri": "occupational-therapy-treatment",
        "name": "Occupational therapy treatment",
        "url": "https://www.sharp.com/chargemaster/memorial/upload/SMH4211.xlsx"
    },
    {
        "hospital_id": "sharp-memorial-hospital",
        "filename": "rehabilitationSMH4411.xlsx",
        "date": "2019-01-19",
        "uri": "outpatient-psychiatric-services",
        "name": "Outpatient psychiatric services",
        "url": "https://www.sharp.com/chargemaster/memorial/upload/SMH4411.xlsx"
    },
    {
        "hospital_id": "sharp-memorial-hospital",
        "filename": "rehabilitationSMH4200.xlsx",
        "date": "2019-01-19",
        "uri": "physical-therapy-clinic",
        "name": "Physical therapy clinic",
        "url": "https://www.sharp.com/chargemaster/memorial/upload/SMH4200.xlsx"
    },
    {
        "hospital_id": "sharp-memorial-hospital",
        "filename": "rehabilitationSMH4201.xlsx",
        "date": "2019-01-19",
        "uri": "physical-therapy-general-treatment",
        "name": "Physical therapy general treatment",
        "url": "https://www.sharp.com/chargemaster/memorial/upload/SMH4201.xlsx"
    },
    {
        "hospital_id": "sharp-memorial-hospital",
        "filename": "rehabilitationSMH4280.xlsx",
        "date": "2019-01-19",
        "uri": "rehab-clinic",
        "name": "Rehab clinic",
        "url": "https://www.sharp.com/chargemaster/memorial/upload/SMH4280.xlsx"
    },
    {
        "hospital_id": "sharp-memorial-hospital",
        "filename": "rehabilitationSMH4413.xlsx",
        "date": "2019-01-19",
        "uri": "rehabilitation-pain-program",
        "name": "Rehabilitation pain program",
        "url": "https://www.sharp.com/chargemaster/memorial/upload/SMH4413.xlsx"
    },
    {
        "hospital_id": "sharp-memorial-hospital",
        "filename": "rehabilitationSMH4414.xlsx",
        "date": "2019-01-19",
        "uri": "rehabilitation-day-treatment",
        "name": "Rehabilitation day treatment",
        "url": "https://www.sharp.com/chargemaster/memorial/upload/SMH4414.xlsx"
    },
    {
        "hospital_id": "sharp-memorial-hospital",
        "filename": "rehabilitationSMH4221.xlsx",
        "date": "2019-01-19",
        "uri": "speech-therapy",
        "name": "Speech therapy",
        "url": "https://www.sharp.com/chargemaster/memorial/upload/SMH4221.xlsx"
    },
    {
        "hospital_id": "sharp-memorial-hospital",
        "filename": "womens-servicesSMH4018.xlsx",
        "date": "2019-01-19",
        "uri": "antenatal-testing",
        "name": "Antenatal testing",
        "url": "https://www.sharp.com/chargemaster/memorial/upload/SMH4018.xlsx"
    },
    {
        "hospital_id": "sharp-memorial-hospital",
        "filename": "womens-servicesSMH4010.xlsx",
        "date": "2019-01-19",
        "uri": "infant-clinic",
        "name": "Infant clinic",
        "url": "https://www.sharp.com/chargemaster/memorial/upload/SMH4010.xlsx"
    },
    {
        "hospital_id": "sharp-memorial-hospital",
        "filename": "womens-servicesSMH4011.xlsx",
        "date": "2019-01-19",
        "uri": "labor-and-delivery",
        "name": "Labor and delivery",
        "url": "https://www.sharp.com/chargemaster/memorial/upload/SMH4011.xlsx"
    },
    {
        "hospital_id": "sharp-memorial-hospital",
        "filename": "womens-servicesSMH4019.xlsx",
        "date": "2019-01-19",
        "uri": "lactation",
        "name": "Lactation",
        "url": "https://www.sharp.com/chargemaster/memorial/upload/SMH4019.xlsx"
    },
    {
        "hospital_id": "sharp-memorial-hospital",
        "filename": "womens-servicesSMH4012.xlsx",
        "date": "2019-01-19",
        "uri": "surgical-gynecology",
        "name": "Surgical gynecology",
        "url": "https://www.sharp.com/chargemaster/memorial/upload/SMH4012.xlsx"
    },
    {
        "hospital_id": "sharp-memorial-hospital",
        "filename": "womens-servicesSMH4016.xlsx",
        "date": "2019-01-19",
        "uri": "women's-center-recovery",
        "name": "Women's center recovery",
        "url": "https://www.sharp.com/chargemaster/memorial/upload/SMH4016.xlsx"
    },
    {
        "hospital_id": "sharp-memorial-hospital",
        "filename": "womens-servicesSMH4014.xlsx",
        "date": "2019-01-19",
        "uri": "women's-triage",
        "name": "Women's triage",
        "url": "https://www.sharp.com/chargemaster/memorial/upload/SMH4014.xlsx"
    }
]